{
"meta":{"test_sets":[],"test_metrics":[],"learn_metrics":[{"best_value":"Min","name":"RMSE"}],"launch_mode":"Train","parameters":"","iteration_count":1000,"learn_sets":["learn"],"name":"experiment"},
"iterations":[
{"learn":[14.59871775],"iteration":0,"passed_time":0.1661858672,"remaining_time":166.0196813},
{"learn":[14.22518863],"iteration":1,"passed_time":0.166983485,"remaining_time":83.32475902},
{"learn":[13.8866124],"iteration":2,"passed_time":0.1676271815,"remaining_time":55.70809998},
{"learn":[13.52356875],"iteration":3,"passed_time":0.1683061275,"remaining_time":41.90822576},
{"learn":[13.18870211],"iteration":4,"passed_time":0.1690410456,"remaining_time":33.63916807},
{"learn":[12.9124226],"iteration":5,"passed_time":0.169660206,"remaining_time":28.1070408},
{"learn":[12.60003351],"iteration":6,"passed_time":0.1703722073,"remaining_time":24.16851456},
{"learn":[12.32990573],"iteration":7,"passed_time":0.1709949856,"remaining_time":21.20337821},
{"learn":[12.0660619],"iteration":8,"passed_time":0.1715672115,"remaining_time":18.89145628},
{"learn":[11.77309809],"iteration":9,"passed_time":0.172125602,"remaining_time":17.0404346},
{"learn":[11.49227636],"iteration":10,"passed_time":0.1727031075,"remaining_time":15.52757939},
{"learn":[11.26264833],"iteration":11,"passed_time":0.1733265169,"remaining_time":14.27054989},
{"learn":[11.04260393],"iteration":12,"passed_time":0.1739869938,"remaining_time":13.20962791},
{"learn":[10.79916926],"iteration":13,"passed_time":0.174572013,"remaining_time":12.29485749},
{"learn":[10.5541002],"iteration":14,"passed_time":0.175153586,"remaining_time":11.50175214},
{"learn":[10.31918115],"iteration":15,"passed_time":0.1757258819,"remaining_time":10.80714174},
{"learn":[10.10004441],"iteration":16,"passed_time":0.1763443022,"remaining_time":10.19684995},
{"learn":[9.894556723],"iteration":17,"passed_time":0.176915386,"remaining_time":9.651717169},
{"learn":[9.690174082],"iteration":18,"passed_time":0.1774944043,"remaining_time":9.164316346},
{"learn":[9.506034866],"iteration":19,"passed_time":0.1780658186,"remaining_time":8.725225113},
{"learn":[9.338524633],"iteration":20,"passed_time":0.1786616176,"remaining_time":8.329034457},
{"learn":[9.170203312],"iteration":21,"passed_time":0.1792826927,"remaining_time":7.969930612},
{"learn":[9.010299969],"iteration":22,"passed_time":0.179915349,"remaining_time":7.642491129},
{"learn":[8.843866678],"iteration":23,"passed_time":0.1805523533,"remaining_time":7.342462366},
{"learn":[8.690548059],"iteration":24,"passed_time":0.1812319754,"remaining_time":7.068047041},
{"learn":[8.555307687],"iteration":25,"passed_time":0.1818124764,"remaining_time":6.810975077},
{"learn":[8.413851302],"iteration":26,"passed_time":0.1824423965,"remaining_time":6.574683399},
{"learn":[8.29256019],"iteration":27,"passed_time":0.1830277363,"remaining_time":6.353677131},
{"learn":[8.162193833],"iteration":28,"passed_time":0.1836471293,"remaining_time":6.1490125},
{"learn":[8.040736294],"iteration":29,"passed_time":0.1843893762,"remaining_time":5.961923163},
{"learn":[7.921220278],"iteration":30,"passed_time":0.1850588148,"remaining_time":5.784580374},
{"learn":[7.809589039],"iteration":31,"passed_time":0.1857920598,"remaining_time":5.62020981},
{"learn":[7.699675801],"iteration":32,"passed_time":0.1865798879,"remaining_time":5.46735611},
{"learn":[7.60645267],"iteration":33,"passed_time":0.1871896925,"remaining_time":5.318389498},
{"learn":[7.498880302],"iteration":34,"passed_time":0.1878610465,"remaining_time":5.179597424},
{"learn":[7.401158744],"iteration":35,"passed_time":0.1884966882,"remaining_time":5.047522429},
{"learn":[7.306431077],"iteration":36,"passed_time":0.189102766,"remaining_time":4.921782801},
{"learn":[7.223863468],"iteration":37,"passed_time":0.1897005886,"remaining_time":4.802420164},
{"learn":[7.143477682],"iteration":38,"passed_time":0.1904795271,"remaining_time":4.693610912},
{"learn":[7.062817131],"iteration":39,"passed_time":0.1912016721,"remaining_time":4.588840131},
{"learn":[6.990793435],"iteration":40,"passed_time":0.1918926751,"remaining_time":4.488416473},
{"learn":[6.931862224],"iteration":41,"passed_time":0.1925289328,"remaining_time":4.391493277},
{"learn":[6.858296558],"iteration":42,"passed_time":0.193211225,"remaining_time":4.300073077},
{"learn":[6.786268161],"iteration":43,"passed_time":0.1937974264,"remaining_time":4.210689537},
{"learn":[6.717118549],"iteration":44,"passed_time":0.194382125,"remaining_time":4.125220653},
{"learn":[6.652948106],"iteration":45,"passed_time":0.1949648901,"remaining_time":4.043402287},
{"learn":[6.589686076],"iteration":46,"passed_time":0.1955463729,"remaining_time":3.965014753},
{"learn":[6.531283097],"iteration":47,"passed_time":0.1964558998,"remaining_time":3.896375346},
{"learn":[6.471368031],"iteration":48,"passed_time":0.1971722494,"remaining_time":3.826751207},
{"learn":[6.416481395],"iteration":49,"passed_time":0.1979257617,"remaining_time":3.760589473},
{"learn":[6.369870822],"iteration":50,"passed_time":0.1986483873,"remaining_time":3.69641803},
{"learn":[6.325678067],"iteration":51,"passed_time":0.1993013559,"remaining_time":3.633417026},
{"learn":[6.275766122],"iteration":52,"passed_time":0.1999599244,"remaining_time":3.572868838},
{"learn":[6.224773967],"iteration":53,"passed_time":0.2005992681,"remaining_time":3.514201992},
{"learn":[6.182249254],"iteration":54,"passed_time":0.2013089798,"remaining_time":3.458854288},
{"learn":[6.139904173],"iteration":55,"passed_time":0.2019167005,"remaining_time":3.403738665},
{"learn":[6.100525536],"iteration":56,"passed_time":0.2026305944,"remaining_time":3.352292114},
{"learn":[6.062568564],"iteration":57,"passed_time":0.2033377769,"remaining_time":3.302485962},
{"learn":[6.030559288],"iteration":58,"passed_time":0.2039519694,"remaining_time":3.252861072},
{"learn":[5.997931376],"iteration":59,"passed_time":0.204546466,"remaining_time":3.2045613},
{"learn":[5.964103835],"iteration":60,"passed_time":0.2051411028,"remaining_time":3.157827795},
{"learn":[5.933729724],"iteration":61,"passed_time":0.2057186985,"remaining_time":3.112324825},
{"learn":[5.901932711],"iteration":62,"passed_time":0.2063080556,"remaining_time":3.068422986},
{"learn":[5.873727795],"iteration":63,"passed_time":0.2068697522,"remaining_time":3.025470127},
{"learn":[5.846485734],"iteration":64,"passed_time":0.2074308978,"remaining_time":2.983813684},
{"learn":[5.820630862],"iteration":65,"passed_time":0.2080646261,"remaining_time":2.944429709},
{"learn":[5.793646238],"iteration":66,"passed_time":0.2087420694,"remaining_time":2.906811205},
{"learn":[5.765388646],"iteration":67,"passed_time":0.2094881931,"remaining_time":2.871220529},
{"learn":[5.747073912],"iteration":68,"passed_time":0.2101767868,"remaining_time":2.835863602},
{"learn":[5.722315217],"iteration":69,"passed_time":0.2108665174,"remaining_time":2.801512303},
{"learn":[5.699970599],"iteration":70,"passed_time":0.211510329,"remaining_time":2.767508389},
{"learn":[5.682732647],"iteration":71,"passed_time":0.2121465117,"remaining_time":2.734332818},
{"learn":[5.663525791],"iteration":72,"passed_time":0.212746899,"remaining_time":2.701594184},
{"learn":[5.642381613],"iteration":73,"passed_time":0.2134384433,"remaining_time":2.670864844},
{"learn":[5.621404779],"iteration":74,"passed_time":0.2142208933,"remaining_time":2.642057685},
{"learn":[5.602460129],"iteration":75,"passed_time":0.2150680717,"remaining_time":2.614774977},
{"learn":[5.587337574],"iteration":76,"passed_time":0.2157742221,"remaining_time":2.586488402},
{"learn":[5.572393026],"iteration":77,"passed_time":0.2164296451,"remaining_time":2.558309395},
{"learn":[5.558425806],"iteration":78,"passed_time":0.2171217801,"remaining_time":2.531255184},
{"learn":[5.541518902],"iteration":79,"passed_time":0.2177970643,"remaining_time":2.50466624},
{"learn":[5.526157283],"iteration":80,"passed_time":0.2184802679,"remaining_time":2.47880699},
{"learn":[5.511746977],"iteration":81,"passed_time":0.219057022,"remaining_time":2.452370076},
{"learn":[5.504975022],"iteration":82,"passed_time":0.2193721079,"remaining_time":2.423665337},
{"learn":[5.493980522],"iteration":83,"passed_time":0.2199390441,"remaining_time":2.398382909},
{"learn":[5.480745463],"iteration":84,"passed_time":0.2205058801,"remaining_time":2.373680944},
{"learn":[5.464052013],"iteration":85,"passed_time":0.2211953502,"remaining_time":2.350843606},
{"learn":[5.449143727],"iteration":86,"passed_time":0.2218319037,"remaining_time":2.327960092},
{"learn":[5.438255432],"iteration":87,"passed_time":0.2224335934,"remaining_time":2.305220877},
{"learn":[5.425927931],"iteration":88,"passed_time":0.2230183221,"remaining_time":2.282805521},
{"learn":[5.412331217],"iteration":89,"passed_time":0.2236431641,"remaining_time":2.261280881},
{"learn":[5.400691499],"iteration":90,"passed_time":0.2242393337,"remaining_time":2.239929169},
{"learn":[5.391618744],"iteration":91,"passed_time":0.2248179112,"remaining_time":2.218855036},
{"learn":[5.380766572],"iteration":92,"passed_time":0.2253759711,"remaining_time":2.198021568},
{"learn":[5.372207183],"iteration":93,"passed_time":0.2259321977,"remaining_time":2.177601821},
{"learn":[5.362918837],"iteration":94,"passed_time":0.2265192006,"remaining_time":2.157893437},
{"learn":[5.348292324],"iteration":95,"passed_time":0.2271931575,"remaining_time":2.139402234},
{"learn":[5.339772295],"iteration":96,"passed_time":0.2278532085,"remaining_time":2.121148941},
{"learn":[5.331515983],"iteration":97,"passed_time":0.2284306639,"remaining_time":2.102494478},
{"learn":[5.323861644],"iteration":98,"passed_time":0.229058151,"remaining_time":2.084660546},
{"learn":[5.313277281],"iteration":99,"passed_time":0.2297113349,"remaining_time":2.067402014},
{"learn":[5.30685627],"iteration":100,"passed_time":0.2302703766,"remaining_time":2.049634342},
{"learn":[5.29652059],"iteration":101,"passed_time":0.2308396871,"remaining_time":2.032294501},
{"learn":[5.288350766],"iteration":102,"passed_time":0.2314054211,"remaining_time":2.015249153},
{"learn":[5.27993346],"iteration":103,"passed_time":0.2319635412,"remaining_time":1.998455124},
{"learn":[5.271789139],"iteration":104,"passed_time":0.2325299464,"remaining_time":1.982040972},
{"learn":[5.262684686],"iteration":105,"passed_time":0.233214326,"remaining_time":1.966920825},
{"learn":[5.251619772],"iteration":106,"passed_time":0.2339455938,"remaining_time":1.952461825},
{"learn":[5.241012171],"iteration":107,"passed_time":0.2345921655,"remaining_time":1.937557515},
{"learn":[5.232684032],"iteration":108,"passed_time":0.2352003972,"remaining_time":1.922601412},
{"learn":[5.224267141],"iteration":109,"passed_time":0.2358562356,"remaining_time":1.90829136},
{"learn":[5.216324968],"iteration":110,"passed_time":0.2364374078,"remaining_time":1.893629329},
{"learn":[5.211102527],"iteration":111,"passed_time":0.237012008,"remaining_time":1.879166635},
{"learn":[5.206364257],"iteration":112,"passed_time":0.2375612819,"remaining_time":1.864750947},
{"learn":[5.196937641],"iteration":113,"passed_time":0.2381635326,"remaining_time":1.850990262},
{"learn":[5.190746047],"iteration":114,"passed_time":0.2387068356,"remaining_time":1.837004778},
{"learn":[5.181885213],"iteration":115,"passed_time":0.2393013425,"remaining_time":1.823641265},
{"learn":[5.178293568],"iteration":116,"passed_time":0.2398248544,"remaining_time":1.809960226},
{"learn":[5.170991438],"iteration":117,"passed_time":0.2404592989,"remaining_time":1.797331369},
{"learn":[5.166257212],"iteration":118,"passed_time":0.2410367342,"remaining_time":1.784482041},
{"learn":[5.161421246],"iteration":119,"passed_time":0.2416115248,"remaining_time":1.771817848},
{"learn":[5.158223542],"iteration":120,"passed_time":0.242165908,"remaining_time":1.759205233},
{"learn":[5.15470988],"iteration":121,"passed_time":0.2426242958,"remaining_time":1.74609944},
{"learn":[5.146388143],"iteration":122,"passed_time":0.2431826964,"remaining_time":1.733912396},
{"learn":[5.139529364],"iteration":123,"passed_time":0.243750384,"remaining_time":1.721978519},
{"learn":[5.134276023],"iteration":124,"passed_time":0.2443055687,"remaining_time":1.710138981},
{"learn":[5.128536065],"iteration":125,"passed_time":0.2448735167,"remaining_time":1.698567092},
{"learn":[5.123300353],"iteration":126,"passed_time":0.2453200528,"remaining_time":1.686333907},
{"learn":[5.116200518],"iteration":127,"passed_time":0.2459832902,"remaining_time":1.675761164},
{"learn":[5.108728704],"iteration":128,"passed_time":0.2466691975,"remaining_time":1.665495124},
{"learn":[5.104075866],"iteration":129,"passed_time":0.2472540473,"remaining_time":1.654700163},
{"learn":[5.100317606],"iteration":130,"passed_time":0.2478153832,"remaining_time":1.6439051},
{"learn":[5.095814182],"iteration":131,"passed_time":0.2483927785,"remaining_time":1.633370695},
{"learn":[5.092146915],"iteration":132,"passed_time":0.2489504879,"remaining_time":1.622857692},
{"learn":[5.085258329],"iteration":133,"passed_time":0.2495070751,"remaining_time":1.612486023},
{"learn":[5.079219421],"iteration":134,"passed_time":0.2500683209,"remaining_time":1.602289612},
{"learn":[5.076476829],"iteration":135,"passed_time":0.2506144691,"remaining_time":1.59213898},
{"learn":[5.072133867],"iteration":136,"passed_time":0.2512016924,"remaining_time":1.582387303},
{"learn":[5.067031564],"iteration":137,"passed_time":0.2518597205,"remaining_time":1.573210718},
{"learn":[5.061358312],"iteration":138,"passed_time":0.2525120528,"remaining_time":1.56412142},
{"learn":[5.056759124],"iteration":139,"passed_time":0.253157317,"remaining_time":1.555109233},
{"learn":[5.050254],"iteration":140,"passed_time":0.2537820084,"remaining_time":1.546090392},
{"learn":[5.048376474],"iteration":141,"passed_time":0.2542654122,"remaining_time":1.536336082},
{"learn":[5.042603751],"iteration":142,"passed_time":0.2548708187,"remaining_time":1.527442599},
{"learn":[5.037477349],"iteration":143,"passed_time":0.2555037155,"remaining_time":1.518827642},
{"learn":[5.03230489],"iteration":144,"passed_time":0.2560768029,"remaining_time":1.509970114},
{"learn":[5.025976187],"iteration":145,"passed_time":0.2567219721,"remaining_time":1.5016477},
{"learn":[5.01952451],"iteration":146,"passed_time":0.257362783,"remaining_time":1.493404448},
{"learn":[5.017569424],"iteration":147,"passed_time":0.2579965568,"remaining_time":1.485223422},
{"learn":[5.008962367],"iteration":148,"passed_time":0.258771443,"remaining_time":1.477949651},
{"learn":[5.003880266],"iteration":149,"passed_time":0.2594456298,"remaining_time":1.470191902},
{"learn":[4.996387564],"iteration":150,"passed_time":0.2601508587,"remaining_time":1.46270251},
{"learn":[4.993361683],"iteration":151,"passed_time":0.260758829,"remaining_time":1.454759783},
{"learn":[4.99005752],"iteration":152,"passed_time":0.2614430259,"remaining_time":1.447334921},
{"learn":[4.986908764],"iteration":153,"passed_time":0.2620380634,"remaining_time":1.439507803},
{"learn":[4.985207175],"iteration":154,"passed_time":0.2626054504,"remaining_time":1.431623262},
{"learn":[4.979003494],"iteration":155,"passed_time":0.2631855908,"remaining_time":1.42390153},
{"learn":[4.973142217],"iteration":156,"passed_time":0.2637555324,"remaining_time":1.416216012},
{"learn":[4.967056696],"iteration":157,"passed_time":0.2643924213,"remaining_time":1.408977334},
{"learn":[4.961460696],"iteration":158,"passed_time":0.2651009059,"remaining_time":1.402200389},
{"learn":[4.954240363],"iteration":159,"passed_time":0.2657008925,"remaining_time":1.394929686},
{"learn":[4.952320707],"iteration":160,"passed_time":0.2660987898,"remaining_time":1.386688724},
{"learn":[4.948337777],"iteration":161,"passed_time":0.2666976746,"remaining_time":1.379584268},
{"learn":[4.943228639],"iteration":162,"passed_time":0.2672681773,"remaining_time":1.372413892},
{"learn":[4.938545759],"iteration":163,"passed_time":0.2678533168,"remaining_time":1.365398615},
{"learn":[4.935330572],"iteration":164,"passed_time":0.2684221565,"remaining_time":1.358378792},
{"learn":[4.932051543],"iteration":165,"passed_time":0.2689978286,"remaining_time":1.351471018},
{"learn":[4.928964153],"iteration":166,"passed_time":0.2695624005,"remaining_time":1.34458371},
{"learn":[4.922860227],"iteration":167,"passed_time":0.270156326,"remaining_time":1.337917043},
{"learn":[4.917668772],"iteration":168,"passed_time":0.270857108,"remaining_time":1.331847673},
{"learn":[4.910365386],"iteration":169,"passed_time":0.2715059126,"remaining_time":1.325587691},
{"learn":[4.906457206],"iteration":170,"passed_time":0.2721147764,"remaining_time":1.319199705},
{"learn":[4.901996508],"iteration":171,"passed_time":0.2727085516,"remaining_time":1.312806283},
{"learn":[4.896816173],"iteration":172,"passed_time":0.2733325621,"remaining_time":1.306624444},
{"learn":[4.891123132],"iteration":173,"passed_time":0.2739064209,"remaining_time":1.300268412},
{"learn":[4.887630202],"iteration":174,"passed_time":0.2744878536,"remaining_time":1.294014167},
{"learn":[4.885259712],"iteration":175,"passed_time":0.275055992,"remaining_time":1.287762144},
{"learn":[4.880659728],"iteration":176,"passed_time":0.2756198426,"remaining_time":1.281554409},
{"learn":[4.877299723],"iteration":177,"passed_time":0.2761821703,"remaining_time":1.275403056},
{"learn":[4.874038772],"iteration":178,"passed_time":0.276837308,"remaining_time":1.269739832},
{"learn":[4.86943698],"iteration":179,"passed_time":0.2774854122,"remaining_time":1.264100211},
{"learn":[4.861268711],"iteration":180,"passed_time":0.2780947562,"remaining_time":1.258340361},
{"learn":[4.858673056],"iteration":181,"passed_time":0.2787070453,"remaining_time":1.252650347},
{"learn":[4.854036207],"iteration":182,"passed_time":0.2792657965,"remaining_time":1.246776808},
{"learn":[4.85130244],"iteration":183,"passed_time":0.2798289959,"remaining_time":1.240980764},
{"learn":[4.847510084],"iteration":184,"passed_time":0.2803746632,"remaining_time":1.235164057},
{"learn":[4.845691673],"iteration":185,"passed_time":0.2809686941,"remaining_time":1.229615683},
{"learn":[4.842058646],"iteration":186,"passed_time":0.2815553363,"remaining_time":1.224088173},
{"learn":[4.838623675],"iteration":187,"passed_time":0.2821204191,"remaining_time":1.218520108},
{"learn":[4.834602161],"iteration":188,"passed_time":0.2827777742,"remaining_time":1.213400925},
{"learn":[4.830858976],"iteration":189,"passed_time":0.2834680157,"remaining_time":1.208468909},
{"learn":[4.827590511],"iteration":190,"passed_time":0.2841337327,"remaining_time":1.203477433},
{"learn":[4.822246226],"iteration":191,"passed_time":0.284728039,"remaining_time":1.198230497},
{"learn":[4.816686395],"iteration":192,"passed_time":0.2852905771,"remaining_time":1.192898942},
{"learn":[4.814797121],"iteration":193,"passed_time":0.2858857148,"remaining_time":1.187751991},
{"learn":[4.811639392],"iteration":194,"passed_time":0.2864743807,"remaining_time":1.182625008},
{"learn":[4.804813432],"iteration":195,"passed_time":0.2870365182,"remaining_time":1.177435513},
{"learn":[4.80251613],"iteration":196,"passed_time":0.2875974133,"remaining_time":1.172287933},
{"learn":[4.800087884],"iteration":197,"passed_time":0.2881787959,"remaining_time":1.167269668},
{"learn":[4.794773135],"iteration":198,"passed_time":0.2887481465,"remaining_time":1.162247565},
{"learn":[4.791664833],"iteration":199,"passed_time":0.2896329989,"remaining_time":1.158531996},
{"learn":[4.785989873],"iteration":200,"passed_time":0.2902894617,"remaining_time":1.153936716},
{"learn":[4.782387142],"iteration":201,"passed_time":0.2910438074,"remaining_time":1.14976712},
{"learn":[4.778623704],"iteration":202,"passed_time":0.2916732979,"remaining_time":1.145140978},
{"learn":[4.775772178],"iteration":203,"passed_time":0.2922625349,"remaining_time":1.14039695},
{"learn":[4.77023101],"iteration":204,"passed_time":0.2929352644,"remaining_time":1.136017245},
{"learn":[4.764496689],"iteration":205,"passed_time":0.2935605773,"remaining_time":1.131490769},
{"learn":[4.763138716],"iteration":206,"passed_time":0.2941969203,"remaining_time":1.127044241},
{"learn":[4.758053283],"iteration":207,"passed_time":0.2953477783,"remaining_time":1.124593464},
{"learn":[4.755063788],"iteration":208,"passed_time":0.2959868154,"remaining_time":1.120218043},
{"learn":[4.752465267],"iteration":209,"passed_time":0.2966490269,"remaining_time":1.115965387},
{"learn":[4.748067377],"iteration":210,"passed_time":0.297288805,"remaining_time":1.111662877},
{"learn":[4.744163298],"iteration":211,"passed_time":0.2978784727,"remaining_time":1.107208663},
{"learn":[4.736670896],"iteration":212,"passed_time":0.2985047486,"remaining_time":1.102925996},
{"learn":[4.73349255],"iteration":213,"passed_time":0.2990848088,"remaining_time":1.098507756},
{"learn":[4.731864595],"iteration":214,"passed_time":0.2996453533,"remaining_time":1.094053964},
{"learn":[4.728398311],"iteration":215,"passed_time":0.3002194025,"remaining_time":1.089685239},
{"learn":[4.723865975],"iteration":216,"passed_time":0.3007791856,"remaining_time":1.085300011},
{"learn":[4.723483365],"iteration":217,"passed_time":0.3013375461,"remaining_time":1.080944775},
{"learn":[4.72095416],"iteration":218,"passed_time":0.3019966905,"remaining_time":1.076983631},
{"learn":[4.716173382],"iteration":219,"passed_time":0.3026269315,"remaining_time":1.07295003},
{"learn":[4.710563974],"iteration":220,"passed_time":0.3032378289,"remaining_time":1.068879044},
{"learn":[4.707160263],"iteration":221,"passed_time":0.3038284584,"remaining_time":1.064768201},
{"learn":[4.70408351],"iteration":222,"passed_time":0.3044017262,"remaining_time":1.060628436},
{"learn":[4.702501831],"iteration":223,"passed_time":0.3049747535,"remaining_time":1.056519682},
{"learn":[4.700269738],"iteration":224,"passed_time":0.3055299883,"remaining_time":1.052381071},
{"learn":[4.695346302],"iteration":225,"passed_time":0.3060909035,"remaining_time":1.048293625},
{"learn":[4.689769299],"iteration":226,"passed_time":0.3066625282,"remaining_time":1.044273719},
{"learn":[4.687919514],"iteration":227,"passed_time":0.3072185845,"remaining_time":1.040231348},
{"learn":[4.682982074],"iteration":228,"passed_time":0.3078231498,"remaining_time":1.036382744},
{"learn":[4.679578702],"iteration":229,"passed_time":0.3084408788,"remaining_time":1.03260642},
{"learn":[4.675751423],"iteration":230,"passed_time":0.309044091,"remaining_time":1.028809117},
{"learn":[4.672710726],"iteration":231,"passed_time":0.3096091237,"remaining_time":1.024912961},
{"learn":[4.6690533],"iteration":232,"passed_time":0.3101769615,"remaining_time":1.021054633},
{"learn":[4.667595702],"iteration":233,"passed_time":0.3107316253,"remaining_time":1.017181303},
{"learn":[4.664241291],"iteration":234,"passed_time":0.3112971589,"remaining_time":1.013371602},
{"learn":[4.662246999],"iteration":235,"passed_time":0.3119192559,"remaining_time":1.009772506},
{"learn":[4.658668443],"iteration":236,"passed_time":0.3125100557,"remaining_time":1.006097774},
{"learn":[4.658017572],"iteration":237,"passed_time":0.313047498,"remaining_time":1.002278124},
{"learn":[4.657656705],"iteration":238,"passed_time":0.3135854713,"remaining_time":0.9984876302},
{"learn":[4.653242871],"iteration":239,"passed_time":0.3142289765,"remaining_time":0.9950584255},
{"learn":[4.6507302],"iteration":240,"passed_time":0.3148422738,"remaining_time":0.9915572024},
{"learn":[4.647671336],"iteration":241,"passed_time":0.3154813366,"remaining_time":0.9881605503},
{"learn":[4.645506007],"iteration":242,"passed_time":0.3160903479,"remaining_time":0.9846929768},
{"learn":[4.641297906],"iteration":243,"passed_time":0.316691717,"remaining_time":0.981225156},
{"learn":[4.63798107],"iteration":244,"passed_time":0.3172605366,"remaining_time":0.9776804293},
{"learn":[4.635062318],"iteration":245,"passed_time":0.3178088688,"remaining_time":0.974097102},
{"learn":[4.631606017],"iteration":246,"passed_time":0.318364304,"remaining_time":0.9705600037},
{"learn":[4.630215494],"iteration":247,"passed_time":0.3189217128,"remaining_time":0.9670529355},
{"learn":[4.62729814],"iteration":248,"passed_time":0.3194824877,"remaining_time":0.9635797119},
{"learn":[4.624691756],"iteration":249,"passed_time":0.3201920415,"remaining_time":0.9605761245},
{"learn":[4.621840053],"iteration":250,"passed_time":0.3209243645,"remaining_time":0.9576587611},
{"learn":[4.619602091],"iteration":251,"passed_time":0.3215839804,"remaining_time":0.954542926},
{"learn":[4.613584029],"iteration":252,"passed_time":0.3221616863,"remaining_time":0.9512046626},
{"learn":[4.6119388],"iteration":253,"passed_time":0.322729464,"remaining_time":0.9478589769},
{"learn":[4.60870702],"iteration":254,"passed_time":0.3233206843,"remaining_time":0.9446035678},
{"learn":[4.604771557],"iteration":255,"passed_time":0.3238810885,"remaining_time":0.9412794135},
{"learn":[4.604231277],"iteration":256,"passed_time":0.3245753374,"remaining_time":0.9383637186},
{"learn":[4.600750354],"iteration":257,"passed_time":0.3251368437,"remaining_time":0.9350834806},
{"learn":[4.596488253],"iteration":258,"passed_time":0.3256923489,"remaining_time":0.9318070678},
{"learn":[4.59470784],"iteration":259,"passed_time":0.3262987977,"remaining_time":0.9286965779},
{"learn":[4.588818005],"iteration":260,"passed_time":0.3270064908,"remaining_time":0.9258919414},
{"learn":[4.585054174],"iteration":261,"passed_time":0.3276568895,"remaining_time":0.9229419255},
{"learn":[4.581471435],"iteration":262,"passed_time":0.3282681868,"remaining_time":0.9198998238},
{"learn":[4.577555199],"iteration":263,"passed_time":0.3288870382,"remaining_time":0.9168971973},
{"learn":[4.57457145],"iteration":264,"passed_time":0.3295404178,"remaining_time":0.9140083286},
{"learn":[4.573029224],"iteration":265,"passed_time":0.3301880818,"remaining_time":0.9111204965},
{"learn":[4.571326203],"iteration":266,"passed_time":0.3309422648,"remaining_time":0.908541873},
{"learn":[4.571019224],"iteration":267,"passed_time":0.3315473307,"remaining_time":0.9055695748},
{"learn":[4.565766631],"iteration":268,"passed_time":0.3321248061,"remaining_time":0.9025399007},
{"learn":[4.563383471],"iteration":269,"passed_time":0.3328077197,"remaining_time":0.8998134645},
{"learn":[4.558165805],"iteration":270,"passed_time":0.3334161666,"remaining_time":0.8969017915},
{"learn":[4.55629209],"iteration":271,"passed_time":0.3341399295,"remaining_time":0.8943156936},
{"learn":[4.549383848],"iteration":272,"passed_time":0.3347264214,"remaining_time":0.8913776863},
{"learn":[4.546227503],"iteration":273,"passed_time":0.3352992283,"remaining_time":0.888420583},
{"learn":[4.540620977],"iteration":274,"passed_time":0.3358694204,"remaining_time":0.8854739266},
{"learn":[4.532898237],"iteration":275,"passed_time":0.336426729,"remaining_time":0.882510695},
{"learn":[4.529757367],"iteration":276,"passed_time":0.3370171081,"remaining_time":0.8796511521},
{"learn":[4.52579294],"iteration":277,"passed_time":0.3376379825,"remaining_time":0.8768871345},
{"learn":[4.521572155],"iteration":278,"passed_time":0.3382040572,"remaining_time":0.8739968645},
{"learn":[4.518818099],"iteration":279,"passed_time":0.3388311581,"remaining_time":0.871280121},
{"learn":[4.514012334],"iteration":280,"passed_time":0.3395227874,"remaining_time":0.8687433599},
{"learn":[4.508331416],"iteration":281,"passed_time":0.3401800988,"remaining_time":0.8661323082},
{"learn":[4.506038537],"iteration":282,"passed_time":0.3407948171,"remaining_time":0.8634271515},
{"learn":[4.505805643],"iteration":283,"passed_time":0.341451232,"remaining_time":0.8608418384},
{"learn":[4.501550352],"iteration":284,"passed_time":0.3420707391,"remaining_time":0.8581774683},
{"learn":[4.494692643],"iteration":285,"passed_time":0.3426874062,"remaining_time":0.8555203078},
{"learn":[4.489330245],"iteration":286,"passed_time":0.3433138363,"remaining_time":0.8529016211},
{"learn":[4.484826955],"iteration":287,"passed_time":0.3439107822,"remaining_time":0.8502238781},
{"learn":[4.478285428],"iteration":288,"passed_time":0.3447053031,"remaining_time":0.8480466107},
{"learn":[4.475311671],"iteration":289,"passed_time":0.3454602128,"remaining_time":0.8457819004},
{"learn":[4.471581298],"iteration":290,"passed_time":0.3462802625,"remaining_time":0.8436862754},
{"learn":[4.469164956],"iteration":291,"passed_time":0.3470974264,"remaining_time":0.84159239},
{"learn":[4.462068024],"iteration":292,"passed_time":0.3477279184,"remaining_time":0.8390567861},
{"learn":[4.458540976],"iteration":293,"passed_time":0.3483435339,"remaining_time":0.8364984181},
{"learn":[4.455757458],"iteration":294,"passed_time":0.3489753186,"remaining_time":0.8339918631},
{"learn":[4.453027414],"iteration":295,"passed_time":0.3495625919,"remaining_time":0.8313921106},
{"learn":[4.450659338],"iteration":296,"passed_time":0.3501378233,"remaining_time":0.8287774066},
{"learn":[4.444696901],"iteration":297,"passed_time":0.3507046092,"remaining_time":0.8261564955},
{"learn":[4.442052813],"iteration":298,"passed_time":0.351351861,"remaining_time":0.8237379751},
{"learn":[4.440036756],"iteration":299,"passed_time":0.352015034,"remaining_time":0.8213684126},
{"learn":[4.435017051],"iteration":300,"passed_time":0.3527015778,"remaining_time":0.8190644615},
{"learn":[4.429962125],"iteration":301,"passed_time":0.3532730824,"remaining_time":0.8165053361},
{"learn":[4.427666256],"iteration":302,"passed_time":0.3538945695,"remaining_time":0.8140743067},
{"learn":[4.425030004],"iteration":303,"passed_time":0.3544855897,"remaining_time":0.811585429},
{"learn":[4.422588771],"iteration":304,"passed_time":0.3550590378,"remaining_time":0.8090689549},
{"learn":[4.418936667],"iteration":305,"passed_time":0.3556284685,"remaining_time":0.8065560691},
{"learn":[4.416887976],"iteration":306,"passed_time":0.3561853563,"remaining_time":0.8040275308},
{"learn":[4.413773354],"iteration":307,"passed_time":0.3567599265,"remaining_time":0.8015515231},
{"learn":[4.411129391],"iteration":308,"passed_time":0.3573266523,"remaining_time":0.7990702807},
{"learn":[4.40850819],"iteration":309,"passed_time":0.3581311879,"remaining_time":0.7971307085},
{"learn":[4.404880292],"iteration":310,"passed_time":0.3588131892,"remaining_time":0.794926969},
{"learn":[4.404593827],"iteration":311,"passed_time":0.359415946,"remaining_time":0.79255824},
{"learn":[4.402139942],"iteration":312,"passed_time":0.3600635044,"remaining_time":0.7902991295},
{"learn":[4.400284725],"iteration":313,"passed_time":0.3606806624,"remaining_time":0.7879838675},
{"learn":[4.395805521],"iteration":314,"passed_time":0.3612623556,"remaining_time":0.7856022653},
{"learn":[4.392838833],"iteration":315,"passed_time":0.3618392499,"remaining_time":0.7832216676},
{"learn":[4.389213061],"iteration":316,"passed_time":0.3624142909,"remaining_time":0.7808484565},
{"learn":[4.3861981],"iteration":317,"passed_time":0.3629913055,"remaining_time":0.7784907874},
{"learn":[4.385054234],"iteration":318,"passed_time":0.3636001283,"remaining_time":0.7762121861},
{"learn":[4.379364607],"iteration":319,"passed_time":0.3643568465,"remaining_time":0.7742582988},
{"learn":[4.378387619],"iteration":320,"passed_time":0.3650501306,"remaining_time":0.7721776905},
{"learn":[4.375816727],"iteration":321,"passed_time":0.3656621792,"remaining_time":0.7699346506},
{"learn":[4.374600202],"iteration":322,"passed_time":0.3663728381,"remaining_time":0.7679083944},
{"learn":[4.37098897],"iteration":323,"passed_time":0.3669655113,"remaining_time":0.7656440915},
{"learn":[4.367418484],"iteration":324,"passed_time":0.3675518029,"remaining_time":0.7633768213},
{"learn":[4.363584638],"iteration":325,"passed_time":0.368121985,"remaining_time":0.7610865579},
{"learn":[4.360770706],"iteration":326,"passed_time":0.3686852445,"remaining_time":0.7587925673},
{"learn":[4.358675808],"iteration":327,"passed_time":0.3692643128,"remaining_time":0.7565415189},
{"learn":[4.354228195],"iteration":328,"passed_time":0.3699079962,"remaining_time":0.7544324179},
{"learn":[4.353773425],"iteration":329,"passed_time":0.3706724635,"remaining_time":0.7525774258},
{"learn":[4.351648009],"iteration":330,"passed_time":0.3713502322,"remaining_time":0.7505537926},
{"learn":[4.348209927],"iteration":331,"passed_time":0.3719386076,"remaining_time":0.7483584032},
{"learn":[4.345852733],"iteration":332,"passed_time":0.3725386843,"remaining_time":0.7461961035},
{"learn":[4.34237339],"iteration":333,"passed_time":0.3731181735,"remaining_time":0.7440021064},
{"learn":[4.340814362],"iteration":334,"passed_time":0.3736880851,"remaining_time":0.7417987361},
{"learn":[4.339707068],"iteration":335,"passed_time":0.3742656407,"remaining_time":0.7396201947},
{"learn":[4.335430786],"iteration":336,"passed_time":0.3748387381,"remaining_time":0.7374423839},
{"learn":[4.33521887],"iteration":337,"passed_time":0.3753734454,"remaining_time":0.7351988783},
{"learn":[4.328507238],"iteration":338,"passed_time":0.3759313651,"remaining_time":0.7330107149},
{"learn":[4.326140732],"iteration":339,"passed_time":0.3766134919,"remaining_time":0.7310732489},
{"learn":[4.323785636],"iteration":340,"passed_time":0.3772732507,"remaining_time":0.7290999185},
{"learn":[4.320632534],"iteration":341,"passed_time":0.3780558811,"remaining_time":0.7273706719},
{"learn":[4.31973724],"iteration":342,"passed_time":0.3786218455,"remaining_time":0.7252319315},
{"learn":[4.318000924],"iteration":343,"passed_time":0.3791992408,"remaining_time":0.7231241337},
{"learn":[4.312713628],"iteration":344,"passed_time":0.3798301439,"remaining_time":0.721126795},
{"learn":[4.308220789],"iteration":345,"passed_time":0.3804996245,"remaining_time":0.7192102729},
{"learn":[4.305890947],"iteration":346,"passed_time":0.381079579,"remaining_time":0.7171324643},
{"learn":[4.305137856],"iteration":347,"passed_time":0.3816613223,"remaining_time":0.7150666153},
{"learn":[4.304787172],"iteration":348,"passed_time":0.3822319552,"remaining_time":0.7129885469},
{"learn":[4.30350134],"iteration":349,"passed_time":0.3828187577,"remaining_time":0.7109491215},
{"learn":[4.30293809],"iteration":350,"passed_time":0.3834236736,"remaining_time":0.7089514649},
{"learn":[4.299548459],"iteration":351,"passed_time":0.3841788426,"remaining_time":0.707238324},
{"learn":[4.294768408],"iteration":352,"passed_time":0.3847978804,"remaining_time":0.7052811009},
{"learn":[4.294581479],"iteration":353,"passed_time":0.3854016776,"remaining_time":0.7033036264},
{"learn":[4.292551604],"iteration":354,"passed_time":0.3860102299,"remaining_time":0.7013425303},
{"learn":[4.288628894],"iteration":355,"passed_time":0.3867189947,"remaining_time":0.6995703162},
{"learn":[4.287802767],"iteration":356,"passed_time":0.3874302862,"remaining_time":0.6978086107},
{"learn":[4.284566905],"iteration":357,"passed_time":0.3880178801,"remaining_time":0.6958309471},
{"learn":[4.27890232],"iteration":358,"passed_time":0.3886113047,"remaining_time":0.6938714383},
{"learn":[4.276938023],"iteration":359,"passed_time":0.3893753466,"remaining_time":0.6922228385},
{"learn":[4.273425094],"iteration":360,"passed_time":0.3900975915,"remaining_time":0.6905051551},
{"learn":[4.269726505],"iteration":361,"passed_time":0.3907586297,"remaining_time":0.6886850988},
{"learn":[4.265565857],"iteration":362,"passed_time":0.3913487683,"remaining_time":0.6867470121},
{"learn":[4.262117173],"iteration":363,"passed_time":0.3919506984,"remaining_time":0.6848369346},
{"learn":[4.259185148],"iteration":364,"passed_time":0.3925413079,"remaining_time":0.6829143302},
{"learn":[4.257668507],"iteration":365,"passed_time":0.3931110993,"remaining_time":0.6809629425},
{"learn":[4.253432436],"iteration":366,"passed_time":0.3936795683,"remaining_time":0.6790168031},
{"learn":[4.250216667],"iteration":367,"passed_time":0.3942343723,"remaining_time":0.6770546829},
{"learn":[4.24514828],"iteration":368,"passed_time":0.3948299609,"remaining_time":0.6751699331},
{"learn":[4.244015772],"iteration":369,"passed_time":0.3954482509,"remaining_time":0.6733308056},
{"learn":[4.240329192],"iteration":370,"passed_time":0.3960555205,"remaining_time":0.6714795752},
{"learn":[4.236718014],"iteration":371,"passed_time":0.396670605,"remaining_time":0.6696482256},
{"learn":[4.233495944],"iteration":372,"passed_time":0.3972690187,"remaining_time":0.6677953746},
{"learn":[4.230357491],"iteration":373,"passed_time":0.3978492091,"remaining_time":0.6659187297},
{"learn":[4.227381215],"iteration":374,"passed_time":0.3984255425,"remaining_time":0.6640425708},
{"learn":[4.226169067],"iteration":375,"passed_time":0.3989976281,"remaining_time":0.6621662764},
{"learn":[4.225963861],"iteration":376,"passed_time":0.399548545,"remaining_time":0.6602619192},
{"learn":[4.224346548],"iteration":377,"passed_time":0.4000947733,"remaining_time":0.658357008},
{"learn":[4.222595381],"iteration":378,"passed_time":0.4006689327,"remaining_time":0.6565050323},
{"learn":[4.219700938],"iteration":379,"passed_time":0.4013089822,"remaining_time":0.6547672868},
{"learn":[4.216356207],"iteration":380,"passed_time":0.4019640449,"remaining_time":0.6530596951},
{"learn":[4.214326494],"iteration":381,"passed_time":0.4026421395,"remaining_time":0.6513948748},
{"learn":[4.212901398],"iteration":382,"passed_time":0.4032522145,"remaining_time":0.6496256301},
{"learn":[4.211331091],"iteration":383,"passed_time":0.4038536337,"remaining_time":0.6478485374},
{"learn":[4.208624791],"iteration":384,"passed_time":0.4044364389,"remaining_time":0.646047818},
{"learn":[4.204659106],"iteration":385,"passed_time":0.4050133032,"remaining_time":0.644243959},
{"learn":[4.202968852],"iteration":386,"passed_time":0.4055590607,"remaining_time":0.6423971685},
{"learn":[4.197261935],"iteration":387,"passed_time":0.4061296836,"remaining_time":0.6405963051},
{"learn":[4.196934403],"iteration":388,"passed_time":0.4066820832,"remaining_time":0.6387731436},
{"learn":[4.192479929],"iteration":389,"passed_time":0.4073224986,"remaining_time":0.6370941644},
{"learn":[4.190243116],"iteration":390,"passed_time":0.4080460112,"remaining_time":0.6355499254},
{"learn":[4.185852431],"iteration":391,"passed_time":0.4087008982,"remaining_time":0.6339034339},
{"learn":[4.180967944],"iteration":392,"passed_time":0.4092798263,"remaining_time":0.6321446681},
{"learn":[4.178283162],"iteration":393,"passed_time":0.4098369746,"remaining_time":0.6303583924},
{"learn":[4.176341157],"iteration":394,"passed_time":0.4103996329,"remaining_time":0.6285867796},
{"learn":[4.176041504],"iteration":395,"passed_time":0.4109736721,"remaining_time":0.6268386312},
{"learn":[4.175564513],"iteration":396,"passed_time":0.4115382941,"remaining_time":0.625082094},
{"learn":[4.170830274],"iteration":397,"passed_time":0.4121042885,"remaining_time":0.6233336224},
{"learn":[4.167804808],"iteration":398,"passed_time":0.4126579304,"remaining_time":0.6215724716},
{"learn":[4.165860548],"iteration":399,"passed_time":0.4132019547,"remaining_time":0.6198029321},
{"learn":[4.160950571],"iteration":400,"passed_time":0.4139207582,"remaining_time":0.6183005839},
{"learn":[4.158544115],"iteration":401,"passed_time":0.4145877573,"remaining_time":0.6167250717},
{"learn":[4.154448767],"iteration":402,"passed_time":0.4153111697,"remaining_time":0.6152376385},
{"learn":[4.15197457],"iteration":403,"passed_time":0.4159135055,"remaining_time":0.6135753695},
{"learn":[4.149562679],"iteration":404,"passed_time":0.4165289087,"remaining_time":0.6119375326},
{"learn":[4.149327961],"iteration":405,"passed_time":0.4170938413,"remaining_time":0.6102308909},
{"learn":[4.147444889],"iteration":406,"passed_time":0.4177259128,"remaining_time":0.6086276814},
{"learn":[4.147254809],"iteration":407,"passed_time":0.418299792,"remaining_time":0.6069447963},
{"learn":[4.144589165],"iteration":408,"passed_time":0.418932438,"remaining_time":0.6053522515},
{"learn":[4.141691034],"iteration":409,"passed_time":0.4195693223,"remaining_time":0.6037704883},
{"learn":[4.138893468],"iteration":410,"passed_time":0.4204077195,"remaining_time":0.602482109},
{"learn":[4.136964597],"iteration":411,"passed_time":0.4211267689,"remaining_time":0.6010255828},
{"learn":[4.133773523],"iteration":412,"passed_time":0.4217862439,"remaining_time":0.5994879544},
{"learn":[4.131363444],"iteration":413,"passed_time":0.4224023703,"remaining_time":0.5978932101},
{"learn":[4.130228592],"iteration":414,"passed_time":0.4229693462,"remaining_time":0.5962338977},
{"learn":[4.12884186],"iteration":415,"passed_time":0.4235837395,"remaining_time":0.5946464035},
{"learn":[4.12413494],"iteration":416,"passed_time":0.4241548633,"remaining_time":0.5930030823},
{"learn":[4.119422508],"iteration":417,"passed_time":0.4247598387,"remaining_time":0.5914120243},
{"learn":[4.117038244],"iteration":418,"passed_time":0.4253352956,"remaining_time":0.5897847417},
{"learn":[4.116067631],"iteration":419,"passed_time":0.4259334641,"remaining_time":0.5881938313},
{"learn":[4.110343455],"iteration":420,"passed_time":0.4268111433,"remaining_time":0.5869920475},
{"learn":[4.105604544],"iteration":421,"passed_time":0.427418338,"remaining_time":0.5854213254},
{"learn":[4.103390131],"iteration":422,"passed_time":0.4280377552,"remaining_time":0.5838718316},
{"learn":[4.096724402],"iteration":423,"passed_time":0.4286471991,"remaining_time":0.5823131761},
{"learn":[4.093431279],"iteration":424,"passed_time":0.4292859514,"remaining_time":0.5807986401},
{"learn":[4.091412744],"iteration":425,"passed_time":0.4299359041,"remaining_time":0.5793033075},
{"learn":[4.091192901],"iteration":426,"passed_time":0.4305905959,"remaining_time":0.5778182938},
{"learn":[4.088994581],"iteration":427,"passed_time":0.4311840754,"remaining_time":0.5762553531},
{"learn":[4.087845355],"iteration":428,"passed_time":0.4318805083,"remaining_time":0.5748339633},
{"learn":[4.083650279],"iteration":429,"passed_time":0.4327365729,"remaining_time":0.5736275501},
{"learn":[4.079840652],"iteration":430,"passed_time":0.4334573248,"remaining_time":0.5722441248},
{"learn":[4.075707828],"iteration":431,"passed_time":0.434123162,"remaining_time":0.5707915649},
{"learn":[4.071345409],"iteration":432,"passed_time":0.4347619495,"remaining_time":0.569307218},
{"learn":[4.067460475],"iteration":433,"passed_time":0.4354174928,"remaining_time":0.5678486197},
{"learn":[4.064914749],"iteration":434,"passed_time":0.4361260278,"remaining_time":0.5664625419},
{"learn":[4.063823175],"iteration":435,"passed_time":0.436736186,"remaining_time":0.564952314},
{"learn":[4.058898471],"iteration":436,"passed_time":0.4373568723,"remaining_time":0.5634597691},
{"learn":[4.054120355],"iteration":437,"passed_time":0.4379739884,"remaining_time":0.5619666243},
{"learn":[4.052715901],"iteration":438,"passed_time":0.43861668,"remaining_time":0.5605101537},
{"learn":[4.052114167],"iteration":439,"passed_time":0.4392507989,"remaining_time":0.5590464714},
{"learn":[4.051377267],"iteration":440,"passed_time":0.4398547127,"remaining_time":0.557548264},
{"learn":[4.049275336],"iteration":441,"passed_time":0.4405515311,"remaining_time":0.55617139},
{"learn":[4.047099198],"iteration":442,"passed_time":0.4411579343,"remaining_time":0.5546839039},
{"learn":[4.044348685],"iteration":443,"passed_time":0.4417971426,"remaining_time":0.5532414668},
{"learn":[4.042822379],"iteration":444,"passed_time":0.4423926161,"remaining_time":0.5517480942},
{"learn":[4.041258611],"iteration":445,"passed_time":0.4430000663,"remaining_time":0.550273625},
{"learn":[4.040044254],"iteration":446,"passed_time":0.4436171873,"remaining_time":0.548814999},
{"learn":[4.036860137],"iteration":447,"passed_time":0.4442448915,"remaining_time":0.5473731699},
{"learn":[4.036372284],"iteration":448,"passed_time":0.4448368033,"remaining_time":0.5458910437},
{"learn":[4.03368231],"iteration":449,"passed_time":0.4457286032,"remaining_time":0.544779404},
{"learn":[4.032439519],"iteration":450,"passed_time":0.446513172,"remaining_time":0.5435382072},
{"learn":[4.032008634],"iteration":451,"passed_time":0.44719149,"remaining_time":0.5421702135},
{"learn":[4.030034932],"iteration":452,"passed_time":0.4478405262,"remaining_time":0.5407699069},
{"learn":[4.028173412],"iteration":453,"passed_time":0.4484516851,"remaining_time":0.5393273569},
{"learn":[4.023806097],"iteration":454,"passed_time":0.44907263,"remaining_time":0.5379001831},
{"learn":[4.020239186],"iteration":455,"passed_time":0.4496353084,"remaining_time":0.5364070345},
{"learn":[4.017384838],"iteration":456,"passed_time":0.4501723199,"remaining_time":0.534887461},
{"learn":[4.016468229],"iteration":457,"passed_time":0.4507703511,"remaining_time":0.5334443892},
{"learn":[4.014530169],"iteration":458,"passed_time":0.4516071122,"remaining_time":0.5322863785},
{"learn":[4.012884822],"iteration":459,"passed_time":0.4523361398,"remaining_time":0.5310032946},
{"learn":[4.008924707],"iteration":460,"passed_time":0.4529868892,"remaining_time":0.5296310917},
{"learn":[4.008286778],"iteration":461,"passed_time":0.4535756152,"remaining_time":0.5281897857},
{"learn":[4.006444202],"iteration":462,"passed_time":0.4542366783,"remaining_time":0.526836061},
{"learn":[4.003284363],"iteration":463,"passed_time":0.4548636393,"remaining_time":0.5254459282},
{"learn":[3.999811484],"iteration":464,"passed_time":0.4554688002,"remaining_time":0.5240339959},
{"learn":[3.997483319],"iteration":465,"passed_time":0.456087481,"remaining_time":0.522641019},
{"learn":[3.99708333],"iteration":466,"passed_time":0.4566831597,"remaining_time":0.5212251052},
{"learn":[3.995860263],"iteration":467,"passed_time":0.4576049727,"remaining_time":0.5201834305},
{"learn":[3.994131111],"iteration":468,"passed_time":0.4584742187,"remaining_time":0.5190827508},
{"learn":[3.993125499],"iteration":469,"passed_time":0.4591148092,"remaining_time":0.5177252103},
{"learn":[3.992954084],"iteration":470,"passed_time":0.4597878994,"remaining_time":0.5164072161},
{"learn":[3.990635743],"iteration":471,"passed_time":0.4603925548,"remaining_time":0.5150154003},
{"learn":[3.986678254],"iteration":472,"passed_time":0.4610708342,"remaining_time":0.5137089421},
{"learn":[3.986393291],"iteration":473,"passed_time":0.4616946647,"remaining_time":0.5123447123},
{"learn":[3.986152671],"iteration":474,"passed_time":0.4623873856,"remaining_time":0.511059742},
{"learn":[3.985596662],"iteration":475,"passed_time":0.4629955571,"remaining_time":0.5096841847},
{"learn":[3.983853457],"iteration":476,"passed_time":0.4636853576,"remaining_time":0.5084013459},
{"learn":[3.983263928],"iteration":477,"passed_time":0.464347553,"remaining_time":0.5070908424},
{"learn":[3.980067202],"iteration":478,"passed_time":0.4649948112,"remaining_time":0.5057667988},
{"learn":[3.978115407],"iteration":479,"passed_time":0.4657250956,"remaining_time":0.5045355202},
{"learn":[3.972661644],"iteration":480,"passed_time":0.4664449464,"remaining_time":0.5032950669},
{"learn":[3.969938254],"iteration":481,"passed_time":0.4670707803,"remaining_time":0.5019557348},
{"learn":[3.968211434],"iteration":482,"passed_time":0.4678110032,"remaining_time":0.5007417984},
{"learn":[3.966113368],"iteration":483,"passed_time":0.4685123754,"remaining_time":0.4994884002},
{"learn":[3.962246044],"iteration":484,"passed_time":0.4692010838,"remaining_time":0.4982238313},
{"learn":[3.961319703],"iteration":485,"passed_time":0.4697863438,"remaining_time":0.4968522237},
{"learn":[3.96078191],"iteration":486,"passed_time":0.4705206258,"remaining_time":0.4956408235},
{"learn":[3.958913633],"iteration":487,"passed_time":0.4711715155,"remaining_time":0.4943438851},
{"learn":[3.957428286],"iteration":488,"passed_time":0.471824188,"remaining_time":0.4930514521},
{"learn":[3.952641965],"iteration":489,"passed_time":0.4725291668,"remaining_time":0.4918160716},
{"learn":[3.951486786],"iteration":490,"passed_time":0.4732635038,"remaining_time":0.490613286},
{"learn":[3.94938344],"iteration":491,"passed_time":0.4738968062,"remaining_time":0.4893080844},
{"learn":[3.947297924],"iteration":492,"passed_time":0.4745207517,"remaining_time":0.487995986},
{"learn":[3.946284886],"iteration":493,"passed_time":0.4751594342,"remaining_time":0.4867017686},
{"learn":[3.943288204],"iteration":494,"passed_time":0.4757996689,"remaining_time":0.4854117834},
{"learn":[3.943076488],"iteration":495,"passed_time":0.4765132081,"remaining_time":0.484198905},
{"learn":[3.942347078],"iteration":496,"passed_time":0.477242471,"remaining_time":0.4830039495},
{"learn":[3.940251541],"iteration":497,"passed_time":0.477875528,"remaining_time":0.4817138857},
{"learn":[3.939011019],"iteration":498,"passed_time":0.4785007407,"remaining_time":0.4804185794},
{"learn":[3.938760512],"iteration":499,"passed_time":0.4790452663,"remaining_time":0.4790452663},
{"learn":[3.934522727],"iteration":500,"passed_time":0.4796626544,"remaining_time":0.4777478334},
{"learn":[3.930091193],"iteration":501,"passed_time":0.4802858285,"remaining_time":0.4764588498},
{"learn":[3.927671752],"iteration":502,"passed_time":0.480894055,"remaining_time":0.4751577442},
{"learn":[3.927280041],"iteration":503,"passed_time":0.4814704837,"remaining_time":0.4738280951},
{"learn":[3.925987561],"iteration":504,"passed_time":0.4820753592,"remaining_time":0.4725293125},
{"learn":[3.921645957],"iteration":505,"passed_time":0.4827397884,"remaining_time":0.471291414},
{"learn":[3.920333743],"iteration":506,"passed_time":0.4834889829,"remaining_time":0.4701382023},
{"learn":[3.918659461],"iteration":507,"passed_time":0.4842361885,"remaining_time":0.4689846551},
{"learn":[3.916124385],"iteration":508,"passed_time":0.4850215339,"remaining_time":0.4678694954},
{"learn":[3.913849268],"iteration":509,"passed_time":0.4856214003,"remaining_time":0.4665774238},
{"learn":[3.912826119],"iteration":510,"passed_time":0.4862898417,"remaining_time":0.4653536841},
{"learn":[3.910034145],"iteration":511,"passed_time":0.486872687,"remaining_time":0.4640505298},
{"learn":[3.90792379],"iteration":512,"passed_time":0.487491528,"remaining_time":0.4627843551},
{"learn":[3.907823851],"iteration":513,"passed_time":0.4880261251,"remaining_time":0.4614410444},
{"learn":[3.904527401],"iteration":514,"passed_time":0.4885944338,"remaining_time":0.4601326221},
{"learn":[3.903378283],"iteration":515,"passed_time":0.4892148626,"remaining_time":0.4588759564},
{"learn":[3.902170135],"iteration":516,"passed_time":0.4898172888,"remaining_time":0.4576049332},
{"learn":[3.899435429],"iteration":517,"passed_time":0.4904314261,"remaining_time":0.4563473888},
{"learn":[3.897497505],"iteration":518,"passed_time":0.4911072064,"remaining_time":0.4551494533},
{"learn":[3.896426119],"iteration":519,"passed_time":0.4917859818,"remaining_time":0.4539562909},
{"learn":[3.896044669],"iteration":520,"passed_time":0.4923624053,"remaining_time":0.4526710022},
{"learn":[3.892795942],"iteration":521,"passed_time":0.4929486067,"remaining_time":0.4513973832},
{"learn":[3.892413888],"iteration":522,"passed_time":0.4935238885,"remaining_time":0.4501164337},
{"learn":[3.891738985],"iteration":523,"passed_time":0.4940800149,"remaining_time":0.4488207769},
{"learn":[3.88822057],"iteration":524,"passed_time":0.494644727,"remaining_time":0.4475357054},
{"learn":[3.883837053],"iteration":525,"passed_time":0.4952903668,"remaining_time":0.4463263001},
{"learn":[3.881769742],"iteration":526,"passed_time":0.4959889035,"remaining_time":0.4451665111},
{"learn":[3.880356898],"iteration":527,"passed_time":0.4967147449,"remaining_time":0.4440328781},
{"learn":[3.879250273],"iteration":528,"passed_time":0.4973518843,"remaining_time":0.44282181},
{"learn":[3.877174493],"iteration":529,"passed_time":0.4980232917,"remaining_time":0.4416432964},
{"learn":[3.875854201],"iteration":530,"passed_time":0.4986230476,"remaining_time":0.4404034074},
{"learn":[3.873189396],"iteration":531,"passed_time":0.4993089649,"remaining_time":0.439241721},
{"learn":[3.871583368],"iteration":532,"passed_time":0.4999275054,"remaining_time":0.4380227861},
{"learn":[3.869622679],"iteration":533,"passed_time":0.5005256049,"remaining_time":0.4367882619},
{"learn":[3.866860164],"iteration":534,"passed_time":0.5012126955,"remaining_time":0.4356334643},
{"learn":[3.864498444],"iteration":535,"passed_time":0.5018884558,"remaining_time":0.4344706035},
{"learn":[3.861416322],"iteration":536,"passed_time":0.502564321,"remaining_time":0.4333096474},
{"learn":[3.860265769],"iteration":537,"passed_time":0.5031941258,"remaining_time":0.4321109407},
{"learn":[3.859328725],"iteration":538,"passed_time":0.5038650684,"remaining_time":0.4309495298},
{"learn":[3.858521278],"iteration":539,"passed_time":0.5045302873,"remaining_time":0.4297850595},
{"learn":[3.85599111],"iteration":540,"passed_time":0.505327872,"remaining_time":0.428734738},
{"learn":[3.852379816],"iteration":541,"passed_time":0.5060107352,"remaining_time":0.4275884072},
{"learn":[3.851327537],"iteration":542,"passed_time":0.506769978,"remaining_time":0.4265080662},
{"learn":[3.847854898],"iteration":543,"passed_time":0.5074404134,"remaining_time":0.4253544641},
{"learn":[3.847083414],"iteration":544,"passed_time":0.5083222952,"remaining_time":0.4243791639},
{"learn":[3.845397429],"iteration":545,"passed_time":0.5090974319,"remaining_time":0.423315447},
{"learn":[3.841933528],"iteration":546,"passed_time":0.5097501196,"remaining_time":0.4221513788},
{"learn":[3.840996474],"iteration":547,"passed_time":0.5104820355,"remaining_time":0.4210545257},
{"learn":[3.838355966],"iteration":548,"passed_time":0.5110720439,"remaining_time":0.4198424259},
{"learn":[3.83342799],"iteration":549,"passed_time":0.5117120955,"remaining_time":0.4186735327},
{"learn":[3.828161535],"iteration":550,"passed_time":0.5124403147,"remaining_time":0.4175784053},
{"learn":[3.823502399],"iteration":551,"passed_time":0.513233947,"remaining_time":0.4165376961},
{"learn":[3.820068862],"iteration":552,"passed_time":0.514069339,"remaining_time":0.4155316357},
{"learn":[3.817951642],"iteration":553,"passed_time":0.5148281759,"remaining_time":0.4144645604},
{"learn":[3.815785958],"iteration":554,"passed_time":0.5155316918,"remaining_time":0.4133542393},
{"learn":[3.81503012],"iteration":555,"passed_time":0.5163298508,"remaining_time":0.41232096},
{"learn":[3.813529315],"iteration":556,"passed_time":0.5169916301,"remaining_time":0.4111800577},
{"learn":[3.808881326],"iteration":557,"passed_time":0.5176199387,"remaining_time":0.4100143601},
{"learn":[3.808740434],"iteration":558,"passed_time":0.5182027637,"remaining_time":0.4088147026},
{"learn":[3.80714352],"iteration":559,"passed_time":0.5187968398,"remaining_time":0.4076260884},
{"learn":[3.80573346],"iteration":560,"passed_time":0.5193527658,"remaining_time":0.4064097401},
{"learn":[3.803370052],"iteration":561,"passed_time":0.5199936119,"remaining_time":0.4052619253},
{"learn":[3.803215211],"iteration":562,"passed_time":0.5206150429,"remaining_time":0.4041008415},
{"learn":[3.801309667],"iteration":563,"passed_time":0.5212263198,"remaining_time":0.4029338217},
{"learn":[3.800003847],"iteration":564,"passed_time":0.5218614008,"remaining_time":0.4017870962},
{"learn":[3.798026138],"iteration":565,"passed_time":0.5224884165,"remaining_time":0.4006359943},
{"learn":[3.794745847],"iteration":566,"passed_time":0.5231260219,"remaining_time":0.399494828},
{"learn":[3.794312041],"iteration":567,"passed_time":0.5238028237,"remaining_time":0.3983852462},
{"learn":[3.792205926],"iteration":568,"passed_time":0.5244765551,"remaining_time":0.3972748598},
{"learn":[3.788991061],"iteration":569,"passed_time":0.5251536207,"remaining_time":0.3961685209},
{"learn":[3.787391572],"iteration":570,"passed_time":0.525775409,"remaining_time":0.3950221549},
{"learn":[3.7826445],"iteration":571,"passed_time":0.5265713188,"remaining_time":0.3940079099},
{"learn":[3.781700331],"iteration":572,"passed_time":0.5272358586,"remaining_time":0.3928965299},
{"learn":[3.780045374],"iteration":573,"passed_time":0.5279956673,"remaining_time":0.3918574116},
{"learn":[3.775462644],"iteration":574,"passed_time":0.5286876821,"remaining_time":0.3907691563},
{"learn":[3.773711943],"iteration":575,"passed_time":0.529362741,"remaining_time":0.3896697955},
{"learn":[3.772415806],"iteration":576,"passed_time":0.5300270801,"remaining_time":0.3885640466},
{"learn":[3.770170875],"iteration":577,"passed_time":0.5306575575,"remaining_time":0.3874351026},
{"learn":[3.765166479],"iteration":578,"passed_time":0.5312917463,"remaining_time":0.3863105789},
{"learn":[3.763976102],"iteration":579,"passed_time":0.5319201649,"remaining_time":0.3851835677},
{"learn":[3.760761708],"iteration":580,"passed_time":0.5326848225,"remaining_time":0.3841565243},
{"learn":[3.758155662],"iteration":581,"passed_time":0.5334659346,"remaining_time":0.3831422005},
{"learn":[3.756844548],"iteration":582,"passed_time":0.5340617336,"remaining_time":0.3819961285},
{"learn":[3.753098923],"iteration":583,"passed_time":0.5347260031,"remaining_time":0.3809007145},
{"learn":[3.751618946],"iteration":584,"passed_time":0.5354435546,"remaining_time":0.3798445729},
{"learn":[3.751398464],"iteration":585,"passed_time":0.5360395539,"remaining_time":0.3787037121},
{"learn":[3.749920103],"iteration":586,"passed_time":0.5366101968,"remaining_time":0.3775468676},
{"learn":[3.748237465],"iteration":587,"passed_time":0.537178185,"remaining_time":0.3763901568},
{"learn":[3.746021536],"iteration":588,"passed_time":0.5377414845,"remaining_time":0.3752321734},
{"learn":[3.74417648],"iteration":589,"passed_time":0.5383003459,"remaining_time":0.3740731217},
{"learn":[3.738788389],"iteration":590,"passed_time":0.5389366188,"remaining_time":0.3729696736},
{"learn":[3.736021611],"iteration":591,"passed_time":0.53960475,"remaining_time":0.3718897601},
{"learn":[3.734546151],"iteration":592,"passed_time":0.5402602016,"remaining_time":0.370802533},
{"learn":[3.733527479],"iteration":593,"passed_time":0.5410088608,"remaining_time":0.3697804672},
{"learn":[3.733026392],"iteration":594,"passed_time":0.5416517261,"remaining_time":0.3686873093},
{"learn":[3.730314752],"iteration":595,"passed_time":0.5423208891,"remaining_time":0.3676134886},
{"learn":[3.727342596],"iteration":596,"passed_time":0.5429343904,"remaining_time":0.3665034495},
{"learn":[3.725459604],"iteration":597,"passed_time":0.5435088002,"remaining_time":0.3653687921},
{"learn":[3.723158842],"iteration":598,"passed_time":0.5440874579,"remaining_time":0.3642388491},
{"learn":[3.722362756],"iteration":599,"passed_time":0.5446527711,"remaining_time":0.3631018474},
{"learn":[3.721443615],"iteration":600,"passed_time":0.5453141602,"remaining_time":0.3620305323},
{"learn":[3.720743486],"iteration":601,"passed_time":0.5460060545,"remaining_time":0.360980747},
{"learn":[3.720215334],"iteration":602,"passed_time":0.5466520451,"remaining_time":0.3599019269},
{"learn":[3.719436563],"iteration":603,"passed_time":0.5473799054,"remaining_time":0.3588782162},
{"learn":[3.715046574],"iteration":604,"passed_time":0.5481114728,"remaining_time":0.3578579037},
{"learn":[3.71443396],"iteration":605,"passed_time":0.5487922419,"remaining_time":0.356805517},
{"learn":[3.712938941],"iteration":606,"passed_time":0.5493832521,"remaining_time":0.3556962407},
{"learn":[3.712814764],"iteration":607,"passed_time":0.55001133,"remaining_time":0.3546125681},
{"learn":[3.71235348],"iteration":608,"passed_time":0.5506031818,"remaining_time":0.3535071331},
{"learn":[3.711223749],"iteration":609,"passed_time":0.5511524056,"remaining_time":0.3523761282},
{"learn":[3.710755648],"iteration":610,"passed_time":0.5518300541,"remaining_time":0.3513287906},
{"learn":[3.708668039],"iteration":611,"passed_time":0.5525379079,"remaining_time":0.3503018109},
{"learn":[3.705623591],"iteration":612,"passed_time":0.5531660708,"remaining_time":0.3492255618},
{"learn":[3.704045802],"iteration":613,"passed_time":0.5538731331,"remaining_time":0.3482003736},
{"learn":[3.699915209],"iteration":614,"passed_time":0.5545294827,"remaining_time":0.3471444729},
{"learn":[3.696182221],"iteration":615,"passed_time":0.5551709251,"remaining_time":0.3460805767},
{"learn":[3.694263278],"iteration":616,"passed_time":0.5557604024,"remaining_time":0.3449857928},
{"learn":[3.693810229],"iteration":617,"passed_time":0.5563064304,"remaining_time":0.3438657871},
{"learn":[3.690900932],"iteration":618,"passed_time":0.5568680769,"remaining_time":0.3427572493},
{"learn":[3.688020895],"iteration":619,"passed_time":0.557434933,"remaining_time":0.3416536686},
{"learn":[3.685491894],"iteration":620,"passed_time":0.5581749859,"remaining_time":0.3406575196},
{"learn":[3.684328128],"iteration":621,"passed_time":0.5588407976,"remaining_time":0.3396170764},
{"learn":[3.680640153],"iteration":622,"passed_time":0.5594944071,"remaining_time":0.3385704518},
{"learn":[3.678932783],"iteration":623,"passed_time":0.5601402174,"remaining_time":0.3375203874},
{"learn":[3.674167041],"iteration":624,"passed_time":0.5607593041,"remaining_time":0.3364555824},
{"learn":[3.672200976],"iteration":625,"passed_time":0.5613624816,"remaining_time":0.3353826967},
{"learn":[3.670606604],"iteration":626,"passed_time":0.5619895277,"remaining_time":0.3343255085},
{"learn":[3.665506042],"iteration":627,"passed_time":0.5625869396,"remaining_time":0.3332521362},
{"learn":[3.664214007],"iteration":628,"passed_time":0.5631419039,"remaining_time":0.3321552406},
{"learn":[3.66261643],"iteration":629,"passed_time":0.5637103328,"remaining_time":0.3310679732},
{"learn":[3.662118449],"iteration":630,"passed_time":0.5643835933,"remaining_time":0.3300436544},
{"learn":[3.660871366],"iteration":631,"passed_time":0.5649812705,"remaining_time":0.328976436},
{"learn":[3.656695243],"iteration":632,"passed_time":0.5656420786,"remaining_time":0.3279473031},
{"learn":[3.654497801],"iteration":633,"passed_time":0.566287463,"remaining_time":0.3269104282},
{"learn":[3.654189134],"iteration":634,"passed_time":0.5669456608,"remaining_time":0.3258821515},
{"learn":[3.653957699],"iteration":635,"passed_time":0.5675348629,"remaining_time":0.3248155505},
{"learn":[3.651920725],"iteration":636,"passed_time":0.5683130151,"remaining_time":0.3238581232},
{"learn":[3.65106705],"iteration":637,"passed_time":0.5688817245,"remaining_time":0.3227824205},
{"learn":[3.650612844],"iteration":638,"passed_time":0.5694308181,"remaining_time":0.3216972228},
{"learn":[3.649884732],"iteration":639,"passed_time":0.5700117851,"remaining_time":0.3206316291},
{"learn":[3.646276182],"iteration":640,"passed_time":0.5707303985,"remaining_time":0.3196446382},
{"learn":[3.645808194],"iteration":641,"passed_time":0.5714048008,"remaining_time":0.3186338297},
{"learn":[3.645042989],"iteration":642,"passed_time":0.5720527551,"remaining_time":0.3176093834},
{"learn":[3.639864499],"iteration":643,"passed_time":0.5727150106,"remaining_time":0.3165940121},
{"learn":[3.637318478],"iteration":644,"passed_time":0.573402447,"remaining_time":0.3155935949},
{"learn":[3.636344905],"iteration":645,"passed_time":0.5740418356,"remaining_time":0.3145678171},
{"learn":[3.634754643],"iteration":646,"passed_time":0.5746153939,"remaining_time":0.3135073169},
{"learn":[3.630724975],"iteration":647,"passed_time":0.5751768601,"remaining_time":0.3124417512},
{"learn":[3.629408252],"iteration":648,"passed_time":0.5757262342,"remaining_time":0.3113711991},
{"learn":[3.62790646],"iteration":649,"passed_time":0.576316588,"remaining_time":0.3103243166},
{"learn":[3.627388973],"iteration":650,"passed_time":0.5771467253,"remaining_time":0.3094073842},
{"learn":[3.625163557],"iteration":651,"passed_time":0.5777575417,"remaining_time":0.3083736572},
{"learn":[3.623701985],"iteration":652,"passed_time":0.5783368405,"remaining_time":0.3073244772},
{"learn":[3.622342639],"iteration":653,"passed_time":0.5790819222,"remaining_time":0.306364442},
{"learn":[3.621130639],"iteration":654,"passed_time":0.5797204095,"remaining_time":0.305348918},
{"learn":[3.619125665],"iteration":655,"passed_time":0.5803001591,"remaining_time":0.304303742},
{"learn":[3.618878783],"iteration":656,"passed_time":0.5808629577,"remaining_time":0.3032511332},
{"learn":[3.616207429],"iteration":657,"passed_time":0.5814116806,"remaining_time":0.3021926972},
{"learn":[3.61206486],"iteration":658,"passed_time":0.5819619864,"remaining_time":0.3011366273},
{"learn":[3.611955873],"iteration":659,"passed_time":0.5825585067,"remaining_time":0.3001058974},
{"learn":[3.610713743],"iteration":660,"passed_time":0.5832842981,"remaining_time":0.2991427792},
{"learn":[3.610044025],"iteration":661,"passed_time":0.5838846705,"remaining_time":0.2981163423},
{"learn":[3.607342669],"iteration":662,"passed_time":0.5844851629,"remaining_time":0.2970912517},
{"learn":[3.602510618],"iteration":663,"passed_time":0.5851337234,"remaining_time":0.2960917636},
{"learn":[3.600492392],"iteration":664,"passed_time":0.5858025507,"remaining_time":0.2951035406},
{"learn":[3.597171065],"iteration":665,"passed_time":0.5864156464,"remaining_time":0.2940883272},
{"learn":[3.594358798],"iteration":666,"passed_time":0.5869746881,"remaining_time":0.293047333},
{"learn":[3.593945251],"iteration":667,"passed_time":0.5875133426,"remaining_time":0.2919976493},
{"learn":[3.593607748],"iteration":668,"passed_time":0.5880587094,"remaining_time":0.2909528144},
{"learn":[3.592238714],"iteration":669,"passed_time":0.5886176109,"remaining_time":0.2899161367},
{"learn":[3.590144654],"iteration":670,"passed_time":0.589393574,"remaining_time":0.2889873112},
{"learn":[3.587151536],"iteration":671,"passed_time":0.5900408722,"remaining_time":0.28799614},
{"learn":[3.586070865],"iteration":672,"passed_time":0.5906386396,"remaining_time":0.2869819244},
{"learn":[3.585102746],"iteration":673,"passed_time":0.5912689167,"remaining_time":0.2859846689},
{"learn":[3.584362847],"iteration":674,"passed_time":0.5918926066,"remaining_time":0.2849853291},
{"learn":[3.581407561],"iteration":675,"passed_time":0.5924794892,"remaining_time":0.2839694593},
{"learn":[3.57919422],"iteration":676,"passed_time":0.5930339125,"remaining_time":0.2829393704},
{"learn":[3.577632204],"iteration":677,"passed_time":0.5935946374,"remaining_time":0.2819136773},
{"learn":[3.573911195],"iteration":678,"passed_time":0.5941665226,"remaining_time":0.28089463},
{"learn":[3.573408216],"iteration":679,"passed_time":0.594704596,"remaining_time":0.2798609864},
{"learn":[3.571076482],"iteration":680,"passed_time":0.5954001324,"remaining_time":0.2789025584},
{"learn":[3.568177107],"iteration":681,"passed_time":0.5960115399,"remaining_time":0.277905674},
{"learn":[3.564824621],"iteration":682,"passed_time":0.5966501868,"remaining_time":0.2769225611},
{"learn":[3.562475026],"iteration":683,"passed_time":0.5972938681,"remaining_time":0.2759427812},
{"learn":[3.561226889],"iteration":684,"passed_time":0.5979314434,"remaining_time":0.2749611747},
{"learn":[3.559383467],"iteration":685,"passed_time":0.5985696049,"remaining_time":0.2739808396},
{"learn":[3.555209766],"iteration":686,"passed_time":0.5991974725,"remaining_time":0.2729968106},
{"learn":[3.55345383],"iteration":687,"passed_time":0.5997649697,"remaining_time":0.2719864398},
{"learn":[3.552300968],"iteration":688,"passed_time":0.6003134522,"remaining_time":0.2709687716},
{"learn":[3.551253986],"iteration":689,"passed_time":0.6008723737,"remaining_time":0.2699571534},
{"learn":[3.549807725],"iteration":690,"passed_time":0.6017243812,"remaining_time":0.2690779071},
{"learn":[3.547992926],"iteration":691,"passed_time":0.60230913,"remaining_time":0.2680797862},
{"learn":[3.545438607],"iteration":692,"passed_time":0.602964683,"remaining_time":0.2671142246},
{"learn":[3.543313763],"iteration":693,"passed_time":0.6037331876,"remaining_time":0.2661993594},
{"learn":[3.542962896],"iteration":694,"passed_time":0.6044673342,"remaining_time":0.2652698373},
{"learn":[3.539800465],"iteration":695,"passed_time":0.6050621513,"remaining_time":0.2642800201},
{"learn":[3.53953187],"iteration":696,"passed_time":0.605626072,"remaining_time":0.2632779051},
{"learn":[3.536332425],"iteration":697,"passed_time":0.606186857,"remaining_time":0.2622756888},
{"learn":[3.534993327],"iteration":698,"passed_time":0.6067493751,"remaining_time":0.261275482},
{"learn":[3.531637011],"iteration":699,"passed_time":0.6073711017,"remaining_time":0.2603019007},
{"learn":[3.531040284],"iteration":700,"passed_time":0.6081251195,"remaining_time":0.25938575},
{"learn":[3.529973872],"iteration":701,"passed_time":0.6087638172,"remaining_time":0.2584211076},
{"learn":[3.527325183],"iteration":702,"passed_time":0.6094520851,"remaining_time":0.2574783347},
{"learn":[3.527200815],"iteration":703,"passed_time":0.6100756548,"remaining_time":0.2565090821},
{"learn":[3.523459911],"iteration":704,"passed_time":0.6108311757,"remaining_time":0.2555960239},
{"learn":[3.522729934],"iteration":705,"passed_time":0.6114073087,"remaining_time":0.2546087093},
{"learn":[3.522260582],"iteration":706,"passed_time":0.61196067,"remaining_time":0.2536131207},
{"learn":[3.518641591],"iteration":707,"passed_time":0.6125194613,"remaining_time":0.2526210208},
{"learn":[3.516856405],"iteration":708,"passed_time":0.6130915469,"remaining_time":0.2516355997},
{"learn":[3.515083413],"iteration":709,"passed_time":0.6137271186,"remaining_time":0.2506772738},
{"learn":[3.514671214],"iteration":710,"passed_time":0.6144226197,"remaining_time":0.2497442153},
{"learn":[3.512617621],"iteration":711,"passed_time":0.6150240186,"remaining_time":0.2487737603},
{"learn":[3.510747971],"iteration":712,"passed_time":0.6156611731,"remaining_time":0.2478187331},
{"learn":[3.508149266],"iteration":713,"passed_time":0.6162910996,"remaining_time":0.246861701},
{"learn":[3.504557165],"iteration":714,"passed_time":0.6169818691,"remaining_time":0.2459298359},
{"learn":[3.501367208],"iteration":715,"passed_time":0.6175609976,"remaining_time":0.2449543622},
{"learn":[3.497593362],"iteration":716,"passed_time":0.6181386333,"remaining_time":0.2439794048},
{"learn":[3.496291169],"iteration":717,"passed_time":0.6186914837,"remaining_time":0.2429958195},
{"learn":[3.49330374],"iteration":718,"passed_time":0.6192414589,"remaining_time":0.2420123087},
{"learn":[3.490044385],"iteration":719,"passed_time":0.6198387105,"remaining_time":0.2410483874},
{"learn":[3.488891789],"iteration":720,"passed_time":0.6205816484,"remaining_time":0.2401418584},
{"learn":[3.486869081],"iteration":721,"passed_time":0.6212439789,"remaining_time":0.2392047453},
{"learn":[3.486303638],"iteration":722,"passed_time":0.6218987557,"remaining_time":0.2382654984},
{"learn":[3.486035862],"iteration":723,"passed_time":0.6225250203,"remaining_time":0.237316168},
{"learn":[3.482668951],"iteration":724,"passed_time":0.6232573469,"remaining_time":0.2364079592},
{"learn":[3.47820549],"iteration":725,"passed_time":0.6238385091,"remaining_time":0.2354431839},
{"learn":[3.474392283],"iteration":726,"passed_time":0.6244097432,"remaining_time":0.2344757357},
{"learn":[3.472268163],"iteration":727,"passed_time":0.6251096794,"remaining_time":0.2335574626},
{"learn":[3.471209164],"iteration":728,"passed_time":0.6257177508,"remaining_time":0.2326056385},
{"learn":[3.470049971],"iteration":729,"passed_time":0.6265499621,"remaining_time":0.2317376572},
{"learn":[3.469078654],"iteration":730,"passed_time":0.6272635961,"remaining_time":0.2308261386},
{"learn":[3.468643292],"iteration":731,"passed_time":0.6280882035,"remaining_time":0.2299557904},
{"learn":[3.468134848],"iteration":732,"passed_time":0.6287970239,"remaining_time":0.2290433907},
{"learn":[3.467820182],"iteration":733,"passed_time":0.6294129997,"remaining_time":0.2280978991},
{"learn":[3.465776156],"iteration":734,"passed_time":0.6301577888,"remaining_time":0.227199747},
{"learn":[3.463037608],"iteration":735,"passed_time":0.6307797656,"remaining_time":0.2262579594},
{"learn":[3.45965637],"iteration":736,"passed_time":0.6313770473,"remaining_time":0.2253082272},
{"learn":[3.457275091],"iteration":737,"passed_time":0.6319999658,"remaining_time":0.2243685515},
{"learn":[3.455522955],"iteration":738,"passed_time":0.6328633808,"remaining_time":0.2235146717},
{"learn":[3.451270508],"iteration":739,"passed_time":0.6336037002,"remaining_time":0.2226175163},
{"learn":[3.450978947],"iteration":740,"passed_time":0.6342217999,"remaining_time":0.221678065},
{"learn":[3.450608492],"iteration":741,"passed_time":0.6348176189,"remaining_time":0.2207317327},
{"learn":[3.448122004],"iteration":742,"passed_time":0.6354606041,"remaining_time":0.2198026585},
{"learn":[3.445646714],"iteration":743,"passed_time":0.63601644,"remaining_time":0.2188443665},
{"learn":[3.44411263],"iteration":744,"passed_time":0.6366193419,"remaining_time":0.2179032647},
{"learn":[3.443264164],"iteration":745,"passed_time":0.6372269224,"remaining_time":0.2169646626},
{"learn":[3.439521363],"iteration":746,"passed_time":0.6378316376,"remaining_time":0.2160259763},
{"learn":[3.436809225],"iteration":747,"passed_time":0.6384042442,"remaining_time":0.2150773657},
{"learn":[3.435509465],"iteration":748,"passed_time":0.6391136908,"remaining_time":0.214175616},
{"learn":[3.434450277],"iteration":749,"passed_time":0.6398039224,"remaining_time":0.2132679741},
{"learn":[3.431786753],"iteration":750,"passed_time":0.6404626062,"remaining_time":0.2123504513},
{"learn":[3.430150302],"iteration":751,"passed_time":0.641106463,"remaining_time":0.2114287272},
{"learn":[3.42696281],"iteration":752,"passed_time":0.6417637844,"remaining_time":0.2105121577},
{"learn":[3.426870334],"iteration":753,"passed_time":0.6423388855,"remaining_time":0.2095694507},
{"learn":[3.425200309],"iteration":754,"passed_time":0.6429553723,"remaining_time":0.2086411473},
{"learn":[3.423383783],"iteration":755,"passed_time":0.6435781906,"remaining_time":0.2077157123},
{"learn":[3.422752979],"iteration":756,"passed_time":0.6441850397,"remaining_time":0.2067859507},
{"learn":[3.420845924],"iteration":757,"passed_time":0.6447994427,"remaining_time":0.2058594527},
{"learn":[3.418917862],"iteration":758,"passed_time":0.6456101092,"remaining_time":0.2049960953},
{"learn":[3.417095735],"iteration":759,"passed_time":0.6463249557,"remaining_time":0.2041026176},
{"learn":[3.414391848],"iteration":760,"passed_time":0.64714355,"remaining_time":0.2032421924},
{"learn":[3.41426711],"iteration":761,"passed_time":0.6477610386,"remaining_time":0.2023190645},
{"learn":[3.411976013],"iteration":762,"passed_time":0.6483809616,"remaining_time":0.201397494},
{"learn":[3.408614844],"iteration":763,"passed_time":0.6490581964,"remaining_time":0.2004944167},
{"learn":[3.407906721],"iteration":764,"passed_time":0.6496981509,"remaining_time":0.1995804777},
{"learn":[3.407494015],"iteration":765,"passed_time":0.6502529248,"remaining_time":0.1986412329},
{"learn":[3.406287128],"iteration":766,"passed_time":0.6508007461,"remaining_time":0.1977008785},
{"learn":[3.404600442],"iteration":767,"passed_time":0.6514504286,"remaining_time":0.196792317},
{"learn":[3.404012662],"iteration":768,"passed_time":0.6521464808,"remaining_time":0.1958983577},
{"learn":[3.400398762],"iteration":769,"passed_time":0.6527725882,"remaining_time":0.1949840198},
{"learn":[3.399737714],"iteration":770,"passed_time":0.6534324742,"remaining_time":0.1940804625},
{"learn":[3.399185251],"iteration":771,"passed_time":0.6540727845,"remaining_time":0.193171755},
{"learn":[3.397245411],"iteration":772,"passed_time":0.6546369356,"remaining_time":0.192241377},
{"learn":[3.396229831],"iteration":773,"passed_time":0.6551879227,"remaining_time":0.1913081015},
{"learn":[3.394002836],"iteration":774,"passed_time":0.6557388696,"remaining_time":0.1903758009},
{"learn":[3.389617243],"iteration":775,"passed_time":0.6562914796,"remaining_time":0.1894449632},
{"learn":[3.385426488],"iteration":776,"passed_time":0.6568386998,"remaining_time":0.1885135522},
{"learn":[3.385072258],"iteration":777,"passed_time":0.6573745291,"remaining_time":0.1875798785},
{"learn":[3.383842366],"iteration":778,"passed_time":0.658285992,"remaining_time":0.1867537923},
{"learn":[3.380110746],"iteration":779,"passed_time":0.6589468899,"remaining_time":0.1858568151},
{"learn":[3.378595218],"iteration":780,"passed_time":0.6596361597,"remaining_time":0.1849683982},
{"learn":[3.377371219],"iteration":781,"passed_time":0.6602711633,"remaining_time":0.1840653627},
{"learn":[3.375814782],"iteration":782,"passed_time":0.6609438297,"remaining_time":0.1831734496},
{"learn":[3.374195887],"iteration":783,"passed_time":0.6615673192,"remaining_time":0.1822685471},
{"learn":[3.373704309],"iteration":784,"passed_time":0.6622370536,"remaining_time":0.1813770274},
{"learn":[3.372971757],"iteration":785,"passed_time":0.6628792473,"remaining_time":0.1804785737},
{"learn":[3.371565136],"iteration":786,"passed_time":0.6634169902,"remaining_time":0.1795525018},
{"learn":[3.3700309],"iteration":787,"passed_time":0.6640337577,"remaining_time":0.1786486759},
{"learn":[3.368186663],"iteration":788,"passed_time":0.6647204826,"remaining_time":0.1777642862},
{"learn":[3.366710398],"iteration":789,"passed_time":0.6653242263,"remaining_time":0.1768583386},
{"learn":[3.364598042],"iteration":790,"passed_time":0.665899097,"remaining_time":0.1759455263},
{"learn":[3.36348442],"iteration":791,"passed_time":0.6664780251,"remaining_time":0.1750346329},
{"learn":[3.362001759],"iteration":792,"passed_time":0.6670474158,"remaining_time":0.1741220871},
{"learn":[3.361580401],"iteration":793,"passed_time":0.6676144321,"remaining_time":0.1732097897},
{"learn":[3.359543675],"iteration":794,"passed_time":0.6681758883,"remaining_time":0.1722969272},
{"learn":[3.35766119],"iteration":795,"passed_time":0.6687517408,"remaining_time":0.1713886371},
{"learn":[3.354592969],"iteration":796,"passed_time":0.6693224338,"remaining_time":0.1704798671},
{"learn":[3.350985986],"iteration":797,"passed_time":0.6698722387,"remaining_time":0.1695666569},
{"learn":[3.349589624],"iteration":798,"passed_time":0.6706438186,"remaining_time":0.1687101471},
{"learn":[3.349110856],"iteration":799,"passed_time":0.6712250409,"remaining_time":0.1678062602},
{"learn":[3.345315441],"iteration":800,"passed_time":0.6717896981,"remaining_time":0.1668990636},
{"learn":[3.34397474],"iteration":801,"passed_time":0.6723836986,"remaining_time":0.1659999655},
{"learn":[3.343800902],"iteration":802,"passed_time":0.6729180252,"remaining_time":0.1650869875},
{"learn":[3.342329465],"iteration":803,"passed_time":0.673454125,"remaining_time":0.1641753837},
{"learn":[3.34220347],"iteration":804,"passed_time":0.6740163225,"remaining_time":0.1632710347},
{"learn":[3.341279219],"iteration":805,"passed_time":0.6746012817,"remaining_time":0.1623730132},
{"learn":[3.337329521],"iteration":806,"passed_time":0.6751617961,"remaining_time":0.1614699215},
{"learn":[3.336708453],"iteration":807,"passed_time":0.6756999597,"remaining_time":0.1605623667},
{"learn":[3.333252703],"iteration":808,"passed_time":0.6762656136,"remaining_time":0.1596622153},
{"learn":[3.332186769],"iteration":809,"passed_time":0.6770765053,"remaining_time":0.1588204148},
{"learn":[3.330594851],"iteration":810,"passed_time":0.6776800788,"remaining_time":0.1579303759},
{"learn":[3.327867442],"iteration":811,"passed_time":0.6784124473,"remaining_time":0.1570708622},
{"learn":[3.327563111],"iteration":812,"passed_time":0.6789798143,"remaining_time":0.1561737088},
{"learn":[3.326308994],"iteration":813,"passed_time":0.6796032237,"remaining_time":0.1552901715},
{"learn":[3.326249879],"iteration":814,"passed_time":0.6801567754,"remaining_time":0.1543914153},
{"learn":[3.322336238],"iteration":815,"passed_time":0.6807250741,"remaining_time":0.1534968304},
{"learn":[3.320491154],"iteration":816,"passed_time":0.6812865002,"remaining_time":0.1526015049},
{"learn":[3.320434271],"iteration":817,"passed_time":0.6818131227,"remaining_time":0.1516992522},
{"learn":[3.319609638],"iteration":818,"passed_time":0.6823587299,"remaining_time":0.1508021125},
{"learn":[3.316182682],"iteration":819,"passed_time":0.6830997646,"remaining_time":0.1499487288},
{"learn":[3.313126612],"iteration":820,"passed_time":0.6837131806,"remaining_time":0.1490677945},
{"learn":[3.311222803],"iteration":821,"passed_time":0.6843582845,"remaining_time":0.148194373},
{"learn":[3.309627335],"iteration":822,"passed_time":0.6850236105,"remaining_time":0.1473258555},
{"learn":[3.307974895],"iteration":823,"passed_time":0.6855941132,"remaining_time":0.1464375776},
{"learn":[3.307321505],"iteration":824,"passed_time":0.6861404417,"remaining_time":0.1455449422},
{"learn":[3.306759087],"iteration":825,"passed_time":0.6867114454,"remaining_time":0.1446583432},
{"learn":[3.30484037],"iteration":826,"passed_time":0.687263334,"remaining_time":0.1437685088},
{"learn":[3.30201994],"iteration":827,"passed_time":0.6878371428,"remaining_time":0.1428840442},
{"learn":[3.299302297],"iteration":828,"passed_time":0.6883995206,"remaining_time":0.1419979711},
{"learn":[3.298132671],"iteration":829,"passed_time":0.6891300911,"remaining_time":0.1411471271},
{"learn":[3.296976183],"iteration":830,"passed_time":0.6897319611,"remaining_time":0.1402703988},
{"learn":[3.293144745],"iteration":831,"passed_time":0.6904064369,"remaining_time":0.1394089921},
{"learn":[3.290284404],"iteration":832,"passed_time":0.6909734031,"remaining_time":0.1385264806},
{"learn":[3.288285745],"iteration":833,"passed_time":0.6915425734,"remaining_time":0.1376451645},
{"learn":[3.286662667],"iteration":834,"passed_time":0.692126691,"remaining_time":0.1367675497},
{"learn":[3.285692682],"iteration":835,"passed_time":0.6926854722,"remaining_time":0.1358856668},
{"learn":[3.284565611],"iteration":836,"passed_time":0.6932291259,"remaining_time":0.1350016099},
{"learn":[3.283897383],"iteration":837,"passed_time":0.6937867851,"remaining_time":0.134121073},
{"learn":[3.280712855],"iteration":838,"passed_time":0.6943494134,"remaining_time":0.1332422593},
{"learn":[3.280468341],"iteration":839,"passed_time":0.694894149,"remaining_time":0.1323607903},
{"learn":[3.277814895],"iteration":840,"passed_time":0.6956612981,"remaining_time":0.1315221717},
{"learn":[3.276316385],"iteration":841,"passed_time":0.6962759916,"remaining_time":0.1306551148},
{"learn":[3.27557063],"iteration":842,"passed_time":0.6970746813,"remaining_time":0.129822924},
{"learn":[3.27499628],"iteration":843,"passed_time":0.6977168402,"remaining_time":0.1289618804},
{"learn":[3.273569958],"iteration":844,"passed_time":0.6982875533,"remaining_time":0.1280882494},
{"learn":[3.269665595],"iteration":845,"passed_time":0.6989302379,"remaining_time":0.1272284357},
{"learn":[3.267984685],"iteration":846,"passed_time":0.6994985065,"remaining_time":0.1263556924},
{"learn":[3.267702508],"iteration":847,"passed_time":0.7000603634,"remaining_time":0.125482518},
{"learn":[3.266671924],"iteration":848,"passed_time":0.7006199963,"remaining_time":0.1246096813},
{"learn":[3.265359825],"iteration":849,"passed_time":0.7011999262,"remaining_time":0.1237411634},
{"learn":[3.2618983],"iteration":850,"passed_time":0.7020362195,"remaining_time":0.12291821},
{"learn":[3.260456253],"iteration":851,"passed_time":0.7027070757,"remaining_time":0.1220664873},
{"learn":[3.258389147],"iteration":852,"passed_time":0.7032858936,"remaining_time":0.1211993275},
{"learn":[3.258108469],"iteration":853,"passed_time":0.7038449654,"remaining_time":0.1203294671},
{"learn":[3.256424936],"iteration":854,"passed_time":0.7044029352,"remaining_time":0.1194601469},
{"learn":[3.254817983],"iteration":855,"passed_time":0.704978958,"remaining_time":0.1185945911},
{"learn":[3.253898449],"iteration":856,"passed_time":0.7055550609,"remaining_time":0.1177297243},
{"learn":[3.253023652],"iteration":857,"passed_time":0.7061110871,"remaining_time":0.1168622079},
{"learn":[3.252845542],"iteration":858,"passed_time":0.7066872053,"remaining_time":0.1159987147},
{"learn":[3.252316026],"iteration":859,"passed_time":0.7072327624,"remaining_time":0.1151309148},
{"learn":[3.24975301],"iteration":860,"passed_time":0.7078403079,"remaining_time":0.1142738709},
{"learn":[3.249151075],"iteration":861,"passed_time":0.7084766158,"remaining_time":0.1134220104},
{"learn":[3.246257135],"iteration":862,"passed_time":0.7090891404,"remaining_time":0.112566874},
{"learn":[3.243826471],"iteration":863,"passed_time":0.7096576996,"remaining_time":0.1117053786},
{"learn":[3.243190653],"iteration":864,"passed_time":0.7102281923,"remaining_time":0.1108448624},
{"learn":[3.24008797],"iteration":865,"passed_time":0.7107816138,"remaining_time":0.1099823744},
{"learn":[3.240036811],"iteration":866,"passed_time":0.7113410262,"remaining_time":0.1091215184},
{"learn":[3.238676314],"iteration":867,"passed_time":0.7118817244,"remaining_time":0.1082585111},
{"learn":[3.237848782],"iteration":868,"passed_time":0.7124681763,"remaining_time":0.1074031428},
{"learn":[3.236405498],"iteration":869,"passed_time":0.7130325878,"remaining_time":0.1065450993},
{"learn":[3.233378068],"iteration":870,"passed_time":0.7135916597,"remaining_time":0.1056869393},
{"learn":[3.233169169],"iteration":871,"passed_time":0.7142880476,"remaining_time":0.1048496217},
{"learn":[3.232434885],"iteration":872,"passed_time":0.7149147579,"remaining_time":0.1040024906},
{"learn":[3.229978115],"iteration":873,"passed_time":0.7155280737,"remaining_time":0.1031539328},
{"learn":[3.229648848],"iteration":874,"passed_time":0.7160998688,"remaining_time":0.1022999813},
{"learn":[3.227208761],"iteration":875,"passed_time":0.7166628377,"remaining_time":0.1014454245},
{"learn":[3.226258869],"iteration":876,"passed_time":0.7172645805,"remaining_time":0.1005969708},
{"learn":[3.225331995],"iteration":877,"passed_time":0.7178208873,"remaining_time":0.09974276566},
{"learn":[3.221968268],"iteration":878,"passed_time":0.718378787,"remaining_time":0.09888945759},
{"learn":[3.221166317],"iteration":879,"passed_time":0.7189291929,"remaining_time":0.09803579904},
{"learn":[3.220047503],"iteration":880,"passed_time":0.7194765133,"remaining_time":0.09718241212},
{"learn":[3.21982781],"iteration":881,"passed_time":0.7199973151,"remaining_time":0.09632617141},
{"learn":[3.216693405],"iteration":882,"passed_time":0.7207294205,"remaining_time":0.09549868878},
{"learn":[3.214798761],"iteration":883,"passed_time":0.7213085089,"remaining_time":0.09465134279},
{"learn":[3.214395085],"iteration":884,"passed_time":0.7218782702,"remaining_time":0.09380339104},
{"learn":[3.213470696],"iteration":885,"passed_time":0.7224442446,"remaining_time":0.09295558001},
{"learn":[3.211595017],"iteration":886,"passed_time":0.7229969648,"remaining_time":0.09210671593},
{"learn":[3.210965255],"iteration":887,"passed_time":0.7235559365,"remaining_time":0.0912593073},
{"learn":[3.209413583],"iteration":888,"passed_time":0.7241355258,"remaining_time":0.09041512189},
{"learn":[3.208331683],"iteration":889,"passed_time":0.7246936459,"remaining_time":0.08956887758},
{"learn":[3.207110711],"iteration":890,"passed_time":0.7252711514,"remaining_time":0.08872565151},
{"learn":[3.204519413],"iteration":891,"passed_time":0.7258272878,"remaining_time":0.08788043395},
{"learn":[3.201421296],"iteration":892,"passed_time":0.7264607155,"remaining_time":0.08704512493},
{"learn":[3.200691259],"iteration":893,"passed_time":0.7271456474,"remaining_time":0.0862163743},
{"learn":[3.200485067],"iteration":894,"passed_time":0.727700772,"remaining_time":0.08537271627},
{"learn":[3.197467568],"iteration":895,"passed_time":0.7283287394,"remaining_time":0.08453815725},
{"learn":[3.195838544],"iteration":896,"passed_time":0.7289033997,"remaining_time":0.08369793776},
{"learn":[3.195671746],"iteration":897,"passed_time":0.7294561099,"remaining_time":0.08285581649},
{"learn":[3.194213094],"iteration":898,"passed_time":0.7300293075,"remaining_time":0.08201664078},
{"learn":[3.192884691],"iteration":899,"passed_time":0.7305879085,"remaining_time":0.08117643428},
{"learn":[3.188364239],"iteration":900,"passed_time":0.7311400977,"remaining_time":0.08033614836},
{"learn":[3.185219478],"iteration":901,"passed_time":0.7316999209,"remaining_time":0.07949733065},
{"learn":[3.184120387],"iteration":902,"passed_time":0.7322634108,"remaining_time":0.07865952475},
{"learn":[3.183725321],"iteration":903,"passed_time":0.7329928343,"remaining_time":0.077839947},
{"learn":[3.181264554],"iteration":904,"passed_time":0.7336400617,"remaining_time":0.07701194018},
{"learn":[3.180741589],"iteration":905,"passed_time":0.7342599748,"remaining_time":0.07618149848},
{"learn":[3.179782639],"iteration":906,"passed_time":0.7348440605,"remaining_time":0.07534784743},
{"learn":[3.176377564],"iteration":907,"passed_time":0.7354056168,"remaining_time":0.07451246338},
{"learn":[3.174078182],"iteration":908,"passed_time":0.7359871397,"remaining_time":0.07367968065},
{"learn":[3.171242379],"iteration":909,"passed_time":0.7367541485,"remaining_time":0.07286579491},
{"learn":[3.170421012],"iteration":910,"passed_time":0.7373344591,"remaining_time":0.07203377263},
{"learn":[3.170087224],"iteration":911,"passed_time":0.7378838633,"remaining_time":0.07119932014},
{"learn":[3.167303059],"iteration":912,"passed_time":0.7384425844,"remaining_time":0.0703663799},
{"learn":[3.16705966],"iteration":913,"passed_time":0.7390627828,"remaining_time":0.0695398242},
{"learn":[3.165667683],"iteration":914,"passed_time":0.7397913745,"remaining_time":0.06872378888},
{"learn":[3.164689733],"iteration":915,"passed_time":0.7403605948,"remaining_time":0.06789332966},
{"learn":[3.163311455],"iteration":916,"passed_time":0.7409249864,"remaining_time":0.06706300313},
{"learn":[3.159425016],"iteration":917,"passed_time":0.7414901493,"remaining_time":0.06623332488},
{"learn":[3.159327058],"iteration":918,"passed_time":0.7420352656,"remaining_time":0.0654024554},
{"learn":[3.15819426],"iteration":919,"passed_time":0.7426037747,"remaining_time":0.06457424128},
{"learn":[3.157086603],"iteration":920,"passed_time":0.7431676553,"remaining_time":0.0637461941},
{"learn":[3.153354154],"iteration":921,"passed_time":0.7437123007,"remaining_time":0.06291709269},
{"learn":[3.153261317],"iteration":922,"passed_time":0.7442595409,"remaining_time":0.06208882411},
{"learn":[3.153168454],"iteration":923,"passed_time":0.7447991171,"remaining_time":0.06126053344},
{"learn":[3.152080399],"iteration":924,"passed_time":0.7454419623,"remaining_time":0.06044124019},
{"learn":[3.151635144],"iteration":925,"passed_time":0.7461307008,"remaining_time":0.05962599553},
{"learn":[3.147762655],"iteration":926,"passed_time":0.7467374097,"remaining_time":0.05880456409},
{"learn":[3.147172317],"iteration":927,"passed_time":0.7473160874,"remaining_time":0.05798142057},
{"learn":[3.146254125],"iteration":928,"passed_time":0.7478850172,"remaining_time":0.05715805836},
{"learn":[3.144869828],"iteration":929,"passed_time":0.7484551392,"remaining_time":0.05633533306},
{"learn":[3.143466218],"iteration":930,"passed_time":0.7490631905,"remaining_time":0.05551596149},
{"learn":[3.141919643],"iteration":931,"passed_time":0.7496767319,"remaining_time":0.05469744396},
{"learn":[3.141054135],"iteration":932,"passed_time":0.7502339804,"remaining_time":0.05387532335},
{"learn":[3.139390417],"iteration":933,"passed_time":0.7508563409,"remaining_time":0.05305837098},
{"learn":[3.139025283],"iteration":934,"passed_time":0.7517025645,"remaining_time":0.05225739753},
{"learn":[3.137824183],"iteration":935,"passed_time":0.7524089255,"remaining_time":0.05144676414},
{"learn":[3.135620453],"iteration":936,"passed_time":0.7530728137,"remaining_time":0.05063349762},
{"learn":[3.13443178],"iteration":937,"passed_time":0.753719611,"remaining_time":0.04981941992},
{"learn":[3.132765713],"iteration":938,"passed_time":0.754357186,"remaining_time":0.04900509941},
{"learn":[3.131434124],"iteration":939,"passed_time":0.754965513,"remaining_time":0.04818928807},
{"learn":[3.128384262],"iteration":940,"passed_time":0.7556186516,"remaining_time":0.04737672736},
{"learn":[3.128120455],"iteration":941,"passed_time":0.7563342094,"remaining_time":0.04656834835},
{"learn":[3.126314615],"iteration":942,"passed_time":0.7569217733,"remaining_time":0.04575242956},
{"learn":[3.125409666],"iteration":943,"passed_time":0.7574912441,"remaining_time":0.04493592126},
{"learn":[3.123072589],"iteration":944,"passed_time":0.7582274828,"remaining_time":0.04412964186},
{"learn":[3.122921099],"iteration":945,"passed_time":0.7588911027,"remaining_time":0.04331936527},
{"learn":[3.122182662],"iteration":946,"passed_time":0.7594752703,"remaining_time":0.04250495177},
{"learn":[3.120040951],"iteration":947,"passed_time":0.7600555609,"remaining_time":0.04169081136},
{"learn":[3.118767799],"iteration":948,"passed_time":0.7606341684,"remaining_time":0.04087707333},
{"learn":[3.118203218],"iteration":949,"passed_time":0.7612124654,"remaining_time":0.04006381397},
{"learn":[3.116343362],"iteration":950,"passed_time":0.7617819663,"remaining_time":0.03925059553},
{"learn":[3.11480829],"iteration":951,"passed_time":0.762350285,"remaining_time":0.0384378295},
{"learn":[3.112607903],"iteration":952,"passed_time":0.7629148068,"remaining_time":0.03762538921},
{"learn":[3.111661241],"iteration":953,"passed_time":0.7634763631,"remaining_time":0.03681332568},
{"learn":[3.110249676],"iteration":954,"passed_time":0.7641468234,"remaining_time":0.03600691838},
{"learn":[3.107333579],"iteration":955,"passed_time":0.7648436621,"remaining_time":0.03520200955},
{"learn":[3.107149851],"iteration":956,"passed_time":0.7653993177,"remaining_time":0.03439098293},
{"learn":[3.106867336],"iteration":957,"passed_time":0.7660195343,"remaining_time":0.03358331987},
{"learn":[3.10364681],"iteration":958,"passed_time":0.7666013276,"remaining_time":0.03277440504},
{"learn":[3.102703811],"iteration":959,"passed_time":0.7671692757,"remaining_time":0.03196538649},
{"learn":[3.101469264],"iteration":960,"passed_time":0.7677326754,"remaining_time":0.03115668506},
{"learn":[3.09863569],"iteration":961,"passed_time":0.7683011043,"remaining_time":0.03034869227},
{"learn":[3.09645939],"iteration":962,"passed_time":0.7688559083,"remaining_time":0.02954067353},
{"learn":[3.096240186],"iteration":963,"passed_time":0.7693839234,"remaining_time":0.02873217971},
{"learn":[3.094838828],"iteration":964,"passed_time":0.7700402499,"remaining_time":0.02792892098},
{"learn":[3.094176802],"iteration":965,"passed_time":0.7708034648,"remaining_time":0.02712972858},
{"learn":[3.093182279],"iteration":966,"passed_time":0.771412518,"remaining_time":0.02632534963},
{"learn":[3.090150687],"iteration":967,"passed_time":0.7721756859,"remaining_time":0.02552646895},
{"learn":[3.088612829],"iteration":968,"passed_time":0.7727471103,"remaining_time":0.02472152778},
{"learn":[3.087153684],"iteration":969,"passed_time":0.7733164308,"remaining_time":0.02391700301},
{"learn":[3.085866843],"iteration":970,"passed_time":0.7738901293,"remaining_time":0.02311309346},
{"learn":[3.082669094],"iteration":971,"passed_time":0.7744412266,"remaining_time":0.02230900653},
{"learn":[3.081047548],"iteration":972,"passed_time":0.7749917127,"remaining_time":0.02150542265},
{"learn":[3.079684322],"iteration":973,"passed_time":0.7755670843,"remaining_time":0.02070302278},
{"learn":[3.07613431],"iteration":974,"passed_time":0.7761311052,"remaining_time":0.01990079757},
{"learn":[3.074005935],"iteration":975,"passed_time":0.7768983544,"remaining_time":0.0191040579},
{"learn":[3.072988853],"iteration":976,"passed_time":0.777514761,"remaining_time":0.01830382754},
{"learn":[3.072344268],"iteration":977,"passed_time":0.778073342,"remaining_time":0.01750267231},
{"learn":[3.070654438],"iteration":978,"passed_time":0.7786260622,"remaining_time":0.01670188693},
{"learn":[3.069724506],"iteration":979,"passed_time":0.7791845329,"remaining_time":0.01590172516},
{"learn":[3.067763166],"iteration":980,"passed_time":0.7798533953,"remaining_time":0.0151041942},
{"learn":[3.066737893],"iteration":981,"passed_time":0.7804164745,"remaining_time":0.01430498629},
{"learn":[3.065248174],"iteration":982,"passed_time":0.7809800044,"remaining_time":0.01350626661},
{"learn":[3.063186837],"iteration":983,"passed_time":0.7815335061,"remaining_time":0.01270786189},
{"learn":[3.062880371],"iteration":984,"passed_time":0.7820793637,"remaining_time":0.01190983803},
{"learn":[3.061288645],"iteration":985,"passed_time":0.782633216,"remaining_time":0.01111243917},
{"learn":[3.059970575],"iteration":986,"passed_time":0.7834214117,"remaining_time":0.01031862042},
{"learn":[3.059576341],"iteration":987,"passed_time":0.7840256361,"remaining_time":0.009522578576},
{"learn":[3.058175919],"iteration":988,"passed_time":0.7846647846,"remaining_time":0.008727313074},
{"learn":[3.056830702],"iteration":989,"passed_time":0.7852407072,"remaining_time":0.007931724315},
{"learn":[3.056336579],"iteration":990,"passed_time":0.785779532,"remaining_time":0.007136241965},
{"learn":[3.055810414],"iteration":991,"passed_time":0.7863320518,"remaining_time":0.006341387515},
{"learn":[3.055476518],"iteration":992,"passed_time":0.7868617499,"remaining_time":0.005546860272},
{"learn":[3.053331734],"iteration":993,"passed_time":0.7874292472,"remaining_time":0.004753094047},
{"learn":[3.050890374],"iteration":994,"passed_time":0.7879878681,"remaining_time":0.003959738031},
{"learn":[3.04972623],"iteration":995,"passed_time":0.7885789384,"remaining_time":0.003166983689},
{"learn":[3.047217327],"iteration":996,"passed_time":0.7893175183,"remaining_time":0.002375077788},
{"learn":[3.047155483],"iteration":997,"passed_time":0.7899827138,"remaining_time":0.001583131691},
{"learn":[3.04430671],"iteration":998,"passed_time":0.7905574643,"remaining_time":0.0007913488131},
{"learn":[3.042664195],"iteration":999,"passed_time":0.7911296,"remaining_time":0}
]}